[
 {
  "input_set_index": 1,
  "input_set_size": 11,
  "input_set_id": 336897,
  "operator": "by_distribution",
  "parameter": "",
  "output_set_count": 2,
  "output_set_average_size": 30.5,
  "reward": 0.8165548580062291,
  "sets_viewed": 2,
  "sets_reviewed": 0,
  "uniformity": 2.228704207228199,
  "diversity": 1.535566955946306,
  "novelty": 0.8154882106352771,
  "utility": 0.8165548580062291,
  "utility_weights": [
   0.005716884856759308,
   0.005716884856759308,
   0.9885662302864814
  ],
  "extrinsic_reward": 0,
  "inverted_entropy_score": 1258.271512235462,
  "galaxy_class_score": 16.479927703079163,
  "class_score_found_12": 130,
  "class_score_found_15": 90,
  "class_score_found_18": 57,
  "class_score_found_21": 29
 },
 {
  "input_set_index": 0,
  "input_set_size": 43,
  "input_set_id": 211521,
  "operator": "by_superset",
  "parameter": "",
  "output_set_count": 3,
  "output_set_average_size": 482.3333333333333,
  "reward": 0.8073498038804398,
  "sets_viewed": 5,
  "sets_reviewed": 0,
  "uniformity": 1.0258689549725797,
  "diversity": -0.8184662034104317,
  "novelty": 0.8154882106352771,
  "utility": 0.8073498038804398,
  "utility_weights": [
   0.014230579087968376,
   0.014230579087968376,
   0.9715388418240632
  ],
  "extrinsic_reward": 0,
  "inverted_entropy_score": 1266.3701237539246,
  "galaxy_class_score": 16.479927703079163,
  "class_score_found_12": 130,
  "class_score_found_15": 90,
  "class_score_found_18": 57,
  "class_score_found_21": 29
 },
 {
  "input_set_index": 1,
  "input_set_size": 290,
  "input_set_id": 88422,
  "operator": "by_distribution",
  "parameter": "",
  "output_set_count": 7,
  "output_set_average_size": 177.85714285714286,
  "reward": 0.8098724875224937,
  "sets_viewed": 12,
  "sets_reviewed": 0,
  "uniformity": 0.10346554703206522,
  "diversity": 1.1328872206212335,
  "novelty": 0.8154882106352771,
  "utility": 0.8098724875224937,
  "utility_weights": [
   0.03380824470911692,
   0.03380824470911692,
   0.9323835105817662
  ],
  "extrinsic_reward": 2.7700831024930745,
  "inverted_entropy_score": 1324.6612470779935,
  "galaxy_class_score": 16.479927703079163,
  "class_score_found_12": 130,
  "class_score_found_15": 90,
  "class_score_found_18": 57,
  "class_score_found_21": 29
 },
 {
  "input_set_index": 5,
  "input_set_size": 276,
  "input_set_id": 90856,
  "operator": "by_facet",
  "parameter": "galaxies.r",
  "output_set_count": 2,
  "output_set_average_size": 138.0,
  "reward": 0.8086592403010576,
  "sets_viewed": 14,
  "sets_reviewed": 0,
  "uniformity": 1.9903940187831424,
  "diversity": -0.5614088689605823,
  "novelty": 0.8154882106352771,
  "utility": 0.8086592403010576,
  "utility_weights": [
   0.039327903793300756,
   0.039327903793300756,
   0.9213441924133985
  ],
  "extrinsic_reward": 0,
  "inverted_entropy_score": 1449.8040414942725,
  "galaxy_class_score": 16.479927703079163,
  "class_score_found_12": 130,
  "class_score_found_15": 90,
  "class_score_found_18": 57,
  "class_score_found_21": 29
 },
 {
  "input_set_index": 0,
  "input_set_size": 265,
  "input_set_id": 92745,
  "operator": "by_distribution",
  "parameter": "",
  "output_set_count": 7,
  "output_set_average_size": 168.42857142857142,
  "reward": 0.7992458157496015,
  "sets_viewed": 21,
  "sets_reviewed": 0,
  "uniformity": 0.09783526039016892,
  "diversity": 1.1201419079570092,
  "novelty": 0.8154882106352771,
  "utility": 0.7992458157496015,
  "utility_weights": [
   0.05838785176143868,
   0.05838785176143868,
   0.8832242964771226
  ],
  "extrinsic_reward": 3.2653061224489797,
  "inverted_entropy_score": 2325.803602408226,
  "galaxy_class_score": 16.479927703079163,
  "class_score_found_12": 130,
  "class_score_found_15": 90,
  "class_score_found_18": 57,
  "class_score_found_21": 29
 },
 {
  "input_set_index": 6,
  "input_set_size": 35,
  "input_set_id": 228464,
  "operator": "by_superset",
  "parameter": "",
  "output_set_count": 3,
  "output_set_average_size": 1217.3333333333333,
  "reward": 0.783134671754829,
  "sets_viewed": 24,
  "sets_reviewed": 0,
  "uniformity": 0.9101275473580922,
  "diversity": 0.1667346548684337,
  "novelty": 0.8154882106352771,
  "utility": 0.783134671754829,
  "utility_weights": [
   0.06643313478278096,
   0.06643313478278096,
   0.8671337304344381
  ],
  "extrinsic_reward": 0.29157858537409925,
  "inverted_entropy_score": 2331.248795993082,
  "galaxy_class_score": 16.479927703079163,
  "class_score_found_12": 130,
  "class_score_found_15": 90,
  "class_score_found_18": 57,
  "class_score_found_21": 29
 },
 {
  "input_set_index": 1,
  "input_set_size": 1115,
  "input_set_id": 38330,
  "operator": "by_distribution",
  "parameter": "",
  "output_set_count": 8,
  "output_set_average_size": 1577.75,
  "reward": 0.7663945857112836,
  "sets_viewed": 32,
  "sets_reviewed": 0,
  "uniformity": -0.15171143371884435,
  "diversity": 1.0436948045407504,
  "novelty": 0.8154882106352771,
  "utility": 0.7663945857112836,
  "utility_weights": [
   0.08752564225663872,
   0.08752564225663872,
   0.8249487154867226
  ],
  "extrinsic_reward": 1.3975019652371385,
  "inverted_entropy_score": 2347.57343994131,
  "galaxy_class_score": 16.479927703079163,
  "class_score_found_12": 130,
  "class_score_found_15": 90,
  "class_score_found_18": 57,
  "class_score_found_21": 29
 },
 {
  "input_set_index": 1,
  "input_set_size": 5903,
  "input_set_id": 9872,
  "operator": "by_superset",
  "parameter": "",
  "output_set_count": 3,
  "output_set_average_size": 22395.0,
  "reward": 0.6546413513712842,
  "sets_viewed": 35,
  "sets_reviewed": 0,
  "uniformity": 0.014327304251831026,
  "diversity": -0.22106215383793704,
  "novelty": 0.8154882106352771,
  "utility": 0.6546413513712842,
  "utility_weights": [
   0.09529973984068973,
   0.09529973984068973,
   0.8094005203186205
  ],
  "extrinsic_reward": 0,
  "inverted_entropy_score": 2349.3023070834247,
  "galaxy_class_score": 16.479927703079163,
  "class_score_found_12": 130,
  "class_score_found_15": 90,
  "class_score_found_18": 57,
  "class_score_found_21": 29
 },
 {
  "input_set_index": 2,
  "input_set_size": 8032,
  "input_set_id": 7336,
  "operator": "by_facet",
  "parameter": "galaxies.z",
  "output_set_count": 3,
  "output_set_average_size": 2677.0,
  "reward": 0.7704562774958211,
  "sets_viewed": 38,
  "sets_reviewed": 0,
  "uniformity": 0.34817661557808655,
  "diversity": 0.8102703610713726,
  "novelty": 0.8154882106352771,
  "utility": 0.7704562774958211,
  "utility_weights": [
   0.10299987776002495,
   0.10299987776002495,
   0.7940002444799501
  ],
  "extrinsic_reward": 0,
  "inverted_entropy_score": 2353.6496914335935,
  "galaxy_class_score": 16.479927703079163,
  "class_score_found_12": 130,
  "class_score_found_15": 90,
  "class_score_found_18": 57,
  "class_score_found_21": 29
 },
 {
  "input_set_index": 0,
  "input_set_size": 7111,
  "input_set_id": 8267,
  "operator": "by_facet",
  "parameter": "galaxies.redshift",
  "output_set_count": 5,
  "output_set_average_size": 1418.2,
  "reward": 0.7110468667834068,
  "sets_viewed": 43,
  "sets_reviewed": 0,
  "uniformity": 0.6049610194906911,
  "diversity": 0.012020568745169815,
  "novelty": 0.8154882106352771,
  "utility": 0.7110468667834068,
  "utility_weights": [
   0.1156690861484374,
   0.1156690861484374,
   0.7686618277031252
  ],
  "extrinsic_reward": 0,
  "inverted_entropy_score": 2979.3636635149896,
  "galaxy_class_score": 16.479927703079163,
  "class_score_found_12": 130,
  "class_score_found_15": 90,
  "class_score_found_18": 57,
  "class_score_found_21": 29
 },
 {
  "input_set_index": 4,
  "input_set_size": 27,
  "input_set_id": 249937,
  "operator": "by_distribution",
  "parameter": "",
  "output_set_count": 3,
  "output_set_average_size": 148.33333333333334,
  "reward": 0.9156189401138048,
  "sets_viewed": 46,
  "sets_reviewed": 0,
  "uniformity": 1.293788653111782,
  "diversity": 1.2028532005806258,
  "novelty": 0.8154882106352771,
  "utility": 0.9156189401138048,
  "utility_weights": [
   0.12317199829519715,
   0.12317199829519715,
   0.7536560034096057
  ],
  "extrinsic_reward": 0,
  "inverted_entropy_score": 3354.7920467638273,
  "galaxy_class_score": 16.479927703079163,
  "class_score_found_12": 130,
  "class_score_found_15": 90,
  "class_score_found_18": 57,
  "class_score_found_21": 29
 },
 {
  "input_set_index": 2,
  "input_set_size": 12,
  "input_set_id": 325564,
  "operator": "by_superset",
  "parameter": "",
  "output_set_count": 3,
  "output_set_average_size": 1121.6666666666667,
  "reward": 0.724917135986054,
  "sets_viewed": 49,
  "sets_reviewed": 0,
  "uniformity": 0.4763807692754897,
  "diversity": 0.4192736964954211,
  "novelty": 0.8154882106352771,
  "utility": 0.724917135986054,
  "utility_weights": [
   0.13060095077724104,
   0.13060095077724104,
   0.7387980984455179
  ],
  "extrinsic_reward": 0.015059594705515777,
  "inverted_entropy_score": 3357.650733779094,
  "galaxy_class_score": 16.479927703079163,
  "class_score_found_12": 130,
  "class_score_found_15": 90,
  "class_score_found_18": 57,
  "class_score_found_21": 29
 },
 {
  "input_set_index": 2,
  "input_set_size": 18,
  "input_set_id": 286108,
  "operator": "by_distribution",
  "parameter": "",
  "output_set_count": 5,
  "output_set_average_size": 501.0,
  "reward": 0.7440641626508409,
  "sets_viewed": 54,
  "sets_reviewed": 0,
  "uniformity": 0.057504356233969066,
  "diversity": 1.0265844079454791,
  "novelty": 0.8154882106352771,
  "utility": 0.7440641626508409,
  "utility_weights": [
   0.14281818343683467,
   0.14281818343683467,
   0.7143636331263307
  ],
  "extrinsic_reward": 0,
  "inverted_entropy_score": 3360.5415856659774,
  "galaxy_class_score": 16.479927703079163,
  "class_score_found_12": 130,
  "class_score_found_15": 90,
  "class_score_found_18": 57,
  "class_score_found_21": 29
 },
 {
  "input_set_index": 3,
  "input_set_size": 42,
  "input_set_id": 212608,
  "operator": "by_facet",
  "parameter": "galaxies.u",
  "output_set_count": 2,
  "output_set_average_size": 11.5,
  "reward": 0.6823588278694693,
  "sets_viewed": 56,
  "sets_reviewed": 0,
  "uniformity": 1.4356858385094047,
  "diversity": -0.7368693114632994,
  "novelty": 0.8154882106352771,
  "utility": 0.6823588278694693,
  "utility_weights": [
   0.14764755231700422,
   0.14764755231700422,
   0.7047048953659916
  ],
  "extrinsic_reward": 0,
  "inverted_entropy_score": 3610.827174498536,
  "galaxy_class_score": 16.479927703079163,
  "class_score_found_12": 130,
  "class_score_found_15": 90,
  "class_score_found_18": 57,
  "class_score_found_21": 29
 },
 {
  "input_set_index": 0,
  "input_set_size": 13,
  "input_set_id": 317067,
  "operator": "by_distribution",
  "parameter": "",
  "output_set_count": 2,
  "output_set_average_size": 75.0,
  "reward": 0.9698937589359697,
  "sets_viewed": 58,
  "sets_reviewed": 0,
  "uniformity": 1.3464337948169114,
  "diversity": 1.330313761007765,
  "novelty": 0.8154882106352771,
  "utility": 0.9698937589359697,
  "utility_weights": [
   0.1524440502350779,
   0.1524440502350779,
   0.6951118995298442
  ],
  "extrinsic_reward": 0,
  "inverted_entropy_score": 3861.1127633310944,
  "galaxy_class_score": 16.479927703079163,
  "class_score_found_12": 130,
  "class_score_found_15": 90,
  "class_score_found_18": 57,
  "class_score_found_21": 29
 },
 {
  "input_set_index": 0,
  "input_set_size": 140,
  "input_set_id": 128260,
  "operator": "by_neighbors",
  "parameter": "galaxies.i",
  "output_set_count": 3,
  "output_set_average_size": 56.0,
  "reward": 0.2499642009500701,
  "sets_viewed": 60,
  "sets_reviewed": 1,
  "uniformity": 1.4006336385255915,
  "diversity": -0.6322037667073129,
  "novelty": 0.19107950685106548,
  "utility": 0.2499642009500701,
  "utility_weights": [
   0.15720767719105572,
   0.15720767719105572,
   0.6855846456178886
  ],
  "extrinsic_reward": 0,
  "inverted_entropy_score": 4111.398352163653,
  "galaxy_class_score": 16.479927703079163,
  "class_score_found_12": 130,
  "class_score_found_15": 90,
  "class_score_found_18": 57,
  "class_score_found_21": 29
 },
 {
  "input_set_index": 1,
  "input_set_size": 10,
  "input_set_id": 345084,
  "operator": "by_superset",
  "parameter": "",
  "output_set_count": 3,
  "output_set_average_size": 109.33333333333333,
  "reward": 0.6040097595468644,
  "sets_viewed": 63,
  "sets_reviewed": 1,
  "uniformity": 0.37500626857274866,
  "diversity": -0.08924691854866554,
  "novelty": 0.8154882106352771,
  "utility": 0.6040097595468644,
  "utility_weights": [
   0.16429148457109255,
   0.16429148457109255,
   0.6714170308578149
  ],
  "extrinsic_reward": 0,
  "inverted_entropy_score": 4115.987929876744,
  "galaxy_class_score": 16.479927703079163,
  "class_score_found_12": 130,
  "class_score_found_15": 90,
  "class_score_found_18": 57,
  "class_score_found_21": 29
 },
 {
  "input_set_index": 1,
  "input_set_size": 81,
  "input_set_id": 163318,
  "operator": "by_distribution",
  "parameter": "",
  "output_set_count": 2,
  "output_set_average_size": 16.5,
  "reward": 0.9778477934254691,
  "sets_viewed": 65,
  "sets_reviewed": 1,
  "uniformity": 1.2712094344752547,
  "diversity": 1.3480079976672625,
  "novelty": 0.8154882106352771,
  "utility": 0.9778477934254691,
  "utility_weights": [
   0.16897293412183045,
   0.16897293412183045,
   0.6620541317563391
  ],
  "extrinsic_reward": 0,
  "inverted_entropy_score": 4118.481281252244,
  "galaxy_class_score": 16.479927703079163,
  "class_score_found_12": 130,
  "class_score_found_15": 90,
  "class_score_found_18": 57,
  "class_score_found_21": 29
 },
 {
  "input_set_index": 1,
  "input_set_size": 15,
  "input_set_id": 300865,
  "operator": "by_superset",
  "parameter": "",
  "output_set_count": 3,
  "output_set_average_size": 125.33333333333333,
  "reward": 0.7035455822140905,
  "sets_viewed": 68,
  "sets_reviewed": 1,
  "uniformity": 0.17623962272787153,
  "diversity": 0.792248282242934,
  "novelty": 0.8154882106352771,
  "utility": 0.7035455822140905,
  "utility_weights": [
   0.17593347539400767,
   0.17593347539400767,
   0.6481330492119847
  ],
  "extrinsic_reward": 0,
  "inverted_entropy_score": 4119.599105542828,
  "galaxy_class_score": 16.479927703079163,
  "class_score_found_12": 130,
  "class_score_found_15": 90,
  "class_score_found_18": 57,
  "class_score_found_21": 29
 },
 {
  "input_set_index": 2,
  "input_set_size": 61,
  "input_set_id": 183721,
  "operator": "by_distribution",
  "parameter": "",
  "output_set_count": 3,
  "output_set_average_size": 347.0,
  "reward": 0.7402580727822093,
  "sets_viewed": 71,
  "sets_reviewed": 1,
  "uniformity": 0.23890294666944314,
  "diversity": 0.9644678828591876,
  "novelty": 0.8154882106352771,
  "utility": 0.7402580727822093,
  "utility_weights": [
   0.18282005700146892,
   0.18282005700146892,
   0.6343598859970622
  ],
  "extrinsic_reward": 0,
  "inverted_entropy_score": 4120.917356887911,
  "galaxy_class_score": 16.479927703079163,
  "class_score_found_12": 130,
  "class_score_found_15": 90,
  "class_score_found_18": 57,
  "class_score_found_21": 29
 },
 {
  "input_set_index": 2,
  "input_set_size": 136,
  "input_set_id": 130015,
  "operator": "by_facet",
  "parameter": "galaxies.u",
  "output_set_count": 7,
  "output_set_average_size": 19.428571428571427,
  "reward": 0.5769785740789695,
  "sets_viewed": 78,
  "sets_reviewed": 1,
  "uniformity": 1.2534524589947476,
  "diversity": -0.9270902057111953,
  "novelty": 0.8154882106352771,
  "utility": 0.5769785740789695,
  "utility_weights": [
   0.19860112650053952,
   0.19860112650053952,
   0.602797746998921
  ],
  "extrinsic_reward": 0,
  "inverted_entropy_score": 4634.769098067917,
  "galaxy_class_score": 16.479927703079163,
  "class_score_found_12": 130,
  "class_score_found_15": 90,
  "class_score_found_18": 57,
  "class_score_found_21": 29
 },
 {
  "input_set_index": 0,
  "input_set_size": 30,
  "input_set_id": 241414,
  "operator": "by_distribution",
  "parameter": "",
  "output_set_count": 3,
  "output_set_average_size": 47.333333333333336,
  "reward": 0.9830163166487746,
  "sets_viewed": 81,
  "sets_reviewed": 1,
  "uniformity": 1.3861180138644114,
  "diversity": 1.0883989701684713,
  "novelty": 0.8154882106352771,
  "utility": 0.9830163166487746,
  "utility_weights": [
   0.20524117589228147,
   0.20524117589228147,
   0.5895176482154371
  ],
  "extrinsic_reward": 0,
  "inverted_entropy_score": 4641.194883907031,
  "galaxy_class_score": 16.479927703079163,
  "class_score_found_12": 130,
  "class_score_found_15": 90,
  "class_score_found_18": 57,
  "class_score_found_21": 29
 },
 {
  "input_set_index": 0,
  "input_set_size": 111,
  "input_set_id": 142573,
  "operator": "by_facet",
  "parameter": "galaxies.z",
  "output_set_count": 2,
  "output_set_average_size": 55.5,
  "reward": 0.6351285330749369,
  "sets_viewed": 83,
  "sets_reviewed": 1,
  "uniformity": 1.5902326583587014,
  "diversity": -0.8380256983145824,
  "novelty": 0.8154882106352771,
  "utility": 0.6351285330749369,
  "utility_weights": [
   0.20962678678415625,
   0.20962678678415625,
   0.5807464264316875
  ],
  "extrinsic_reward": 0,
  "inverted_entropy_score": 4891.480472739589,
  "galaxy_class_score": 16.479927703079163,
  "class_score_found_12": 130,
  "class_score_found_15": 90,
  "class_score_found_18": 57,
  "class_score_found_21": 29
 },
 {
  "input_set_index": 0,
  "input_set_size": 100,
  "input_set_id": 148858,
  "operator": "by_distribution",
  "parameter": "",
  "output_set_count": 2,
  "output_set_average_size": 23.5,
  "reward": 0.6126230304711343,
  "sets_viewed": 84,
  "sets_reviewed": 2,
  "uniformity": 1.5509579285596085,
  "diversity": 1.8969347869896809,
  "novelty": -0.1896656365890159,
  "utility": 0.6126230304711343,
  "utility_weights": [
   0.21180726561930763,
   0.21180726561930763,
   0.5763854687613847
  ],
  "extrinsic_reward": 0,
  "inverted_entropy_score": 5016.623267155867,
  "galaxy_class_score": 16.479927703079163,
  "class_score_found_12": 130,
  "class_score_found_15": 90,
  "class_score_found_18": 57,
  "class_score_found_21": 29
 },
 {
  "input_set_index": 1,
  "input_set_size": 30,
  "input_set_id": 241414,
  "operator": "by_superset",
  "parameter": "",
  "output_set_count": 3,
  "output_set_average_size": 273.0,
  "reward": 0.503096037341752,
  "sets_viewed": 87,
  "sets_reviewed": 2,
  "uniformity": -0.6281088196553067,
  "diversity": 0.7841963962013178,
  "novelty": 0.8154882106352771,
  "utility": 0.503096037341752,
  "utility_weights": [
   0.218299395681618,
   0.218299395681618,
   0.563401208636764
  ],
  "extrinsic_reward": 0,
  "inverted_entropy_score": 5018.544026797992,
  "galaxy_class_score": 16.479927703079163,
  "class_score_found_12": 130,
  "class_score_found_15": 90,
  "class_score_found_18": 57,
  "class_score_found_21": 29
 },
 {
  "input_set_index": 2,
  "input_set_size": 132,
  "input_set_id": 131486,
  "operator": "by_distribution",
  "parameter": "",
  "output_set_count": 3,
  "output_set_average_size": 272.6666666666667,
  "reward": 0.7396607681256738,
  "sets_viewed": 90,
  "sets_reviewed": 2,
  "uniformity": 0.2757558086804049,
  "diversity": 1.0078653564162159,
  "novelty": 0.8154882106352771,
  "utility": 0.7396607681256738,
  "utility_weights": [
   0.22471756607921256,
   0.22471756607921256,
   0.5505648678415749
  ],
  "extrinsic_reward": 0,
  "inverted_entropy_score": 5020.116802204519,
  "galaxy_class_score": 16.479927703079163,
  "class_score_found_12": 130,
  "class_score_found_15": 90,
  "class_score_found_18": 57,
  "class_score_found_21": 29
 },
 {
  "input_set_index": 2,
  "input_set_size": 24,
  "input_set_id": 260433,
  "operator": "by_superset",
  "parameter": "",
  "output_set_count": 3,
  "output_set_average_size": 410.6666666666667,
  "reward": 0.49192343516507053,
  "sets_viewed": 93,
  "sets_reviewed": 2,
  "uniformity": -0.24614078957954216,
  "diversity": 0.4372441243102106,
  "novelty": 0.8154882106352771,
  "utility": 0.49192343516507053,
  "utility_weights": [
   0.23106177681209128,
   0.23106177681209128,
   0.5378764463758174
  ],
  "extrinsic_reward": 0,
  "inverted_entropy_score": 5020.978803479582,
  "galaxy_class_score": 16.479927703079163,
  "class_score_found_12": 130,
  "class_score_found_15": 90,
  "class_score_found_18": 57,
  "class_score_found_21": 29
 },
 {
  "input_set_index": 2,
  "input_set_size": 92,
  "input_set_id": 154613,
  "operator": "by_distribution",
  "parameter": "",
  "output_set_count": 3,
  "output_set_average_size": 571.0,
  "reward": 0.7135609597731771,
  "sets_viewed": 96,
  "sets_reviewed": 2,
  "uniformity": 0.12390463650906161,
  "diversity": 1.0659462456594915,
  "novelty": 0.8154882106352771,
  "utility": 0.7135609597731771,
  "utility_weights": [
   0.2373320278802542,
   0.2373320278802542,
   0.5253359442394916
  ],
  "extrinsic_reward": 0,
  "inverted_entropy_score": 5022.032062022537,
  "galaxy_class_score": 16.479927703079163,
  "class_score_found_12": 130,
  "class_score_found_15": 90,
  "class_score_found_18": 57,
  "class_score_found_21": 29
 },
 {
  "input_set_index": 0,
  "input_set_size": 296,
  "input_set_id": 87420,
  "operator": "by_facet",
  "parameter": "galaxies.u",
  "output_set_count": 7,
  "output_set_average_size": 42.285714285714285,
  "reward": 0.4313083729249513,
  "sets_viewed": 103,
  "sets_reviewed": 2,
  "uniformity": 0.8034042905113312,
  "diversity": -0.7911720444018459,
  "novelty": 0.8154882106352771,
  "utility": 0.4313083729249513,
  "utility_weights": [
   0.25167499278762856,
   0.25167499278762856,
   0.4966500144247429
  ],
  "extrinsic_reward": 0,
  "inverted_entropy_score": 5027.237091476799,
  "galaxy_class_score": 16.479927703079163,
  "class_score_found_12": 130,
  "class_score_found_15": 90,
  "class_score_found_18": 57,
  "class_score_found_21": 29
 },
 {
  "input_set_index": 4,
  "input_set_size": 40,
  "input_set_id": 216758,
  "operator": "by_distribution",
  "parameter": "",
  "output_set_count": 2,
  "output_set_average_size": 80.5,
  "reward": 1.167471407411397,
  "sets_viewed": 105,
  "sets_reviewed": 2,
  "uniformity": 1.1274366025402458,
  "diversity": 1.9021022777074492,
  "novelty": 0.8154882106352771,
  "utility": 1.167471407411397,
  "utility_weights": [
   0.2556990230964482,
   0.2556990230964482,
   0.4886019538071036
  ],
  "extrinsic_reward": 0,
  "inverted_entropy_score": 5028.742171041922,
  "galaxy_class_score": 16.479927703079163,
  "class_score_found_12": 130,
  "class_score_found_15": 90,
  "class_score_found_18": 57,
  "class_score_found_21": 29
 },
 {
  "input_set_index": 1,
  "input_set_size": 144,
  "input_set_id": 126497,
  "operator": "by_facet",
  "parameter": "galaxies.g",
  "output_set_count": 3,
  "output_set_average_size": 45.666666666666664,
  "reward": 0.5299395814540216,
  "sets_viewed": 108,
  "sets_reviewed": 2,
  "uniformity": 1.504734622828198,
  "diversity": -0.9904954722884285,
  "novelty": 0.8154882106352771,
  "utility": 0.5299395814540216,
  "utility_weights": [
   0.261673435505748,
   0.261673435505748,
   0.476653128988504
  ],
  "extrinsic_reward": 0,
  "inverted_entropy_score": 5404.170554290758,
  "galaxy_class_score": 16.479927703079163,
  "class_score_found_12": 130,
  "class_score_found_15": 90,
  "class_score_found_18": 57,
  "class_score_found_21": 29
 },
 {
  "input_set_index": 1,
  "input_set_size": 37,
  "input_set_id": 223266,
  "operator": "by_neighbors",
  "parameter": "galaxies.redshift",
  "output_set_count": 3,
  "output_set_average_size": 24.0,
  "reward": 0.2801565640602145,
  "sets_viewed": 110,
  "sets_reviewed": 3,
  "uniformity": 1.2205605181846935,
  "diversity": -0.49798843566269635,
  "novelty": 0.19107950685106548,
  "utility": 0.2801565640602145,
  "utility_weights": [
   0.26561528840932785,
   0.26561528840932785,
   0.4687694231813443
  ],
  "extrinsic_reward": 0,
  "inverted_entropy_score": 5654.456143123316,
  "galaxy_class_score": 16.479927703079163,
  "class_score_found_12": 130,
  "class_score_found_15": 90,
  "class_score_found_18": 57,
  "class_score_found_21": 29
 },
 {
  "input_set_index": 1,
  "input_set_size": 11,
  "input_set_id": 337301,
  "operator": "by_distribution",
  "parameter": "",
  "output_set_count": 3,
  "output_set_average_size": 28.0,
  "reward": 0.5393498036379054,
  "sets_viewed": 113,
  "sets_reviewed": 3,
  "uniformity": -0.7513856390072908,
  "diversity": 1.3427441653476888,
  "novelty": 0.8154882106352771,
  "utility": 0.5393498036379054,
  "utility_weights": [
   0.2714664347107679,
   0.2714664347107679,
   0.4570671305784642
  ],
  "extrinsic_reward": 0,
  "inverted_entropy_score": 6029.884526372152,
  "galaxy_class_score": 16.479927703079163,
  "class_score_found_12": 130,
  "class_score_found_15": 90,
  "class_score_found_18": 57,
  "class_score_found_21": 29
 },
 {
  "input_set_index": 1,
  "input_set_size": 47,
  "input_set_id": 203363,
  "operator": "by_superset",
  "parameter": "",
  "output_set_count": 3,
  "output_set_average_size": 446.0,
  "reward": 0.5366842391759351,
  "sets_viewed": 116,
  "sets_reviewed": 3,
  "uniformity": 0.266270454166387,
  "diversity": 0.33767670745963013,
  "novelty": 0.8154882106352771,
  "utility": 0.5366842391759351,
  "utility_weights": [
   0.27724362134749214,
   0.27724362134749214,
   0.44551275730501577
  ],
  "extrinsic_reward": 0,
  "inverted_entropy_score": 6031.66620416145,
  "galaxy_class_score": 16.479927703079163,
  "class_score_found_12": 130,
  "class_score_found_15": 90,
  "class_score_found_18": 57,
  "class_score_found_21": 29
 },
 {
  "input_set_index": 0,
  "input_set_size": 789,
  "input_set_id": 48439,
  "operator": "by_distribution",
  "parameter": "",
  "output_set_count": 3,
  "output_set_average_size": 280.3333333333333,
  "reward": 0.5817041653470154,
  "sets_viewed": 119,
  "sets_reviewed": 3,
  "uniformity": -0.5070773452115007,
  "diversity": 1.2948096761329353,
  "novelty": 0.8154882106352771,
  "utility": 0.5817041653470154,
  "utility_weights": [
   0.28294684831950057,
   0.28294684831950057,
   0.4341063033609989
  ],
  "extrinsic_reward": 0,
  "inverted_entropy_score": 6033.157119857605,
  "galaxy_class_score": 16.479927703079163,
  "class_score_found_12": 130,
  "class_score_found_15": 90,
  "class_score_found_18": 57,
  "class_score_found_21": 29
 },
 {
  "input_set_index": 0,
  "input_set_size": 162,
  "input_set_id": 119353,
  "operator": "by_superset",
  "parameter": "",
  "output_set_count": 3,
  "output_set_average_size": 1270.6666666666667,
  "reward": 0.41504911570952585,
  "sets_viewed": 122,
  "sets_reviewed": 3,
  "uniformity": -0.40059380984235193,
  "diversity": 0.6163252926940138,
  "novelty": 0.8154882106352771,
  "utility": 0.41504911570952585,
  "utility_weights": [
   0.2885761156267932,
   0.2885761156267932,
   0.42284776874641367
  ],
  "extrinsic_reward": 0,
  "inverted_entropy_score": 6034.192790907112,
  "galaxy_class_score": 16.479927703079163,
  "class_score_found_12": 130,
  "class_score_found_15": 90,
  "class_score_found_18": 57,
  "class_score_found_21": 29
 },
 {
  "input_set_index": 1,
  "input_set_size": 1274,
  "input_set_id": 34920,
  "operator": "by_distribution",
  "parameter": "",
  "output_set_count": 3,
  "output_set_average_size": 777.3333333333334,
  "reward": 0.442379169616985,
  "sets_viewed": 125,
  "sets_reviewed": 3,
  "uniformity": -0.692153047573659,
  "diversity": 1.0301983466413527,
  "novelty": 0.8154882106352771,
  "utility": 0.442379169616985,
  "utility_weights": [
   0.29413142326937,
   0.29413142326937,
   0.41173715346126005
  ],
  "extrinsic_reward": 0,
  "inverted_entropy_score": 6035.28683445623,
  "galaxy_class_score": 16.479927703079163,
  "class_score_found_12": 130,
  "class_score_found_15": 90,
  "class_score_found_18": 57,
  "class_score_found_21": 29
 },
 {
  "input_set_index": 2,
  "input_set_size": 179,
  "input_set_id": 113792,
  "operator": "by_superset",
  "parameter": "",
  "output_set_count": 3,
  "output_set_average_size": 1715.3333333333333,
  "reward": 0.19225882195652033,
  "sets_viewed": 128,
  "sets_reviewed": 3,
  "uniformity": -0.7546498310288925,
  "diversity": 0.26674557728909953,
  "novelty": 0.8154882106352771,
  "utility": 0.19225882195652033,
  "utility_weights": [
   0.29961277124723096,
   0.29961277124723096,
   0.40077445750553803
  ],
  "extrinsic_reward": 0,
  "inverted_entropy_score": 6036.012625452478,
  "galaxy_class_score": 16.479927703079163,
  "class_score_found_12": 130,
  "class_score_found_15": 90,
  "class_score_found_18": 57,
  "class_score_found_21": 29
 },
 {
  "input_set_index": 1,
  "input_set_size": 982,
  "input_set_id": 41787,
  "operator": "by_distribution",
  "parameter": "",
  "output_set_count": 4,
  "output_set_average_size": 2075.75,
  "reward": 0.43336339289157,
  "sets_viewed": 132,
  "sets_reviewed": 3,
  "uniformity": -0.6665471780088831,
  "diversity": 1.0221279739427933,
  "novelty": 0.8154882106352771,
  "utility": 0.43336339289157,
  "utility_weights": [
   0.30680618685037664,
   0.30680618685037664,
   0.38638762629924667
  ],
  "extrinsic_reward": 0,
  "inverted_entropy_score": 6037.113328720202,
  "galaxy_class_score": 16.479927703079163,
  "class_score_found_12": 130,
  "class_score_found_15": 90,
  "class_score_found_18": 57,
  "class_score_found_21": 29
 },
 {
  "input_set_index": 3,
  "input_set_size": 50,
  "input_set_id": 198914,
  "operator": "by_facet",
  "parameter": "galaxies.petroRad_r",
  "output_set_count": 3,
  "output_set_average_size": 12.0,
  "reward": 0.41951523526952494,
  "sets_viewed": 135,
  "sets_reviewed": 3,
  "uniformity": 1.130320762435314,
  "diversity": -0.789973384310035,
  "novelty": 0.8154882106352771,
  "utility": 0.41951523526952494,
  "utility_weights": [
   0.312114962277234,
   0.312114962277234,
   0.3757700754455319
  ],
  "extrinsic_reward": 0,
  "inverted_entropy_score": 6039.632755127721,
  "galaxy_class_score": 16.479927703079163,
  "class_score_found_12": 130,
  "class_score_found_15": 90,
  "class_score_found_18": 57,
  "class_score_found_21": 29
 },
 {
  "input_set_index": 2,
  "input_set_size": 10,
  "input_set_id": 343808,
  "operator": "by_distribution",
  "parameter": "",
  "output_set_count": 2,
  "output_set_average_size": 211.0,
  "reward": 0.6555624961024346,
  "sets_viewed": 137,
  "sets_reviewed": 3,
  "uniformity": -0.4221562884552667,
  "diversity": 1.540739092431724,
  "novelty": 0.8154882106352771,
  "utility": 0.6555624961024346,
  "utility_weights": [
   0.3156130571925192,
   0.3156130571925192,
   0.36877388561496155
  ],
  "extrinsic_reward": 0,
  "inverted_entropy_score": 6040.730899934947,
  "galaxy_class_score": 16.479927703079163,
  "class_score_found_12": 130,
  "class_score_found_15": 90,
  "class_score_found_18": 57,
  "class_score_found_21": 29
 },
 {
  "input_set_index": 0,
  "input_set_size": 69,
  "input_set_id": 175159,
  "operator": "by_facet",
  "parameter": "galaxies.g",
  "output_set_count": 3,
  "output_set_average_size": 22.666666666666668,
  "reward": 0.39134657358518854,
  "sets_viewed": 140,
  "sets_reviewed": 3,
  "uniformity": 1.2097912640746282,
  "diversity": -0.9226807804904497,
  "novelty": 0.8154882106352771,
  "utility": 0.39134657358518854,
  "utility_weights": [
   0.32079856651151695,
   0.32079856651151695,
   0.35840286697696616
  ],
  "extrinsic_reward": 0,
  "inverted_entropy_score": 6045.571002029199,
  "galaxy_class_score": 16.479927703079163,
  "class_score_found_12": 130,
  "class_score_found_15": 90,
  "class_score_found_18": 57,
  "class_score_found_21": 29
 },
 {
  "input_set_index": 0,
  "input_set_size": 43,
  "input_set_id": 211594,
  "operator": "by_facet",
  "parameter": "galaxies.i",
  "output_set_count": 2,
  "output_set_average_size": 21.5,
  "reward": 0.39724725132929145,
  "sets_viewed": 142,
  "sets_reviewed": 3,
  "uniformity": 1.2909653035448034,
  "diversity": -0.9637383467874282,
  "novelty": 0.8154882106352771,
  "utility": 0.39724725132929145,
  "utility_weights": [
   0.3242144840215622,
   0.3242144840215622,
   0.35157103195687556
  ],
  "extrinsic_reward": 0,
  "inverted_entropy_score": 6295.856590861757,
  "galaxy_class_score": 16.479927703079163,
  "class_score_found_12": 130,
  "class_score_found_15": 90,
  "class_score_found_18": 57,
  "class_score_found_21": 29
 },
 {
  "input_set_index": 0,
  "input_set_size": 28,
  "input_set_id": 246633,
  "operator": "by_superset",
  "parameter": "",
  "output_set_count": 3,
  "output_set_average_size": 260.6666666666667,
  "reward": 0.32550493924710633,
  "sets_viewed": 145,
  "sets_reviewed": 3,
  "uniformity": 0.06925085596259664,
  "diversity": 0.05043197561261274,
  "novelty": 0.8154882106352771,
  "utility": 0.32550493924710633,
  "utility_weights": [
   0.3292767272327003,
   0.3292767272327003,
   0.34144654553459935
  ],
  "extrinsic_reward": 0,
  "inverted_entropy_score": 6298.530509347411,
  "galaxy_class_score": 16.479927703079163,
  "class_score_found_12": 130,
  "class_score_found_15": 90,
  "class_score_found_18": 57,
  "class_score_found_21": 29
 },
 {
  "input_set_index": 1,
  "input_set_size": 319,
  "input_set_id": 83978,
  "operator": "by_distribution",
  "parameter": "",
  "output_set_count": 4,
  "output_set_average_size": 413.0,
  "reward": 0.6006382823690237,
  "sets_viewed": 149,
  "sets_reviewed": 3,
  "uniformity": 0.002536404579758617,
  "diversity": 0.9759495413635837,
  "novelty": 0.8154882106352771,
  "utility": 0.6006382823690237,
  "utility_weights": [
   0.3359113364802155,
   0.3359113364802155,
   0.32817732703956903
  ],
  "extrinsic_reward": 0,
  "inverted_entropy_score": 6300.625369731635,
  "galaxy_class_score": 16.479927703079163,
  "class_score_found_12": 130,
  "class_score_found_15": 90,
  "class_score_found_18": 57,
  "class_score_found_21": 29
 },
 {
  "input_set_index": 2,
  "input_set_size": 162,
  "input_set_id": 119519,
  "operator": "by_superset",
  "parameter": "",
  "output_set_count": 3,
  "output_set_average_size": 1184.0,
  "reward": 0.3387359098848171,
  "sets_viewed": 152,
  "sets_reviewed": 3,
  "uniformity": -0.1363817063760781,
  "diversity": 0.34807795167513833,
  "novelty": 0.8154882106352771,
  "utility": 0.3387359098848171,
  "utility_weights": [
   0.34080100714035,
   0.34080100714035,
   0.31839798571930006
  ],
  "extrinsic_reward": 0,
  "inverted_entropy_score": 6301.609018554225,
  "galaxy_class_score": 16.479927703079163,
  "class_score_found_12": 130,
  "class_score_found_15": 90,
  "class_score_found_18": 57,
  "class_score_found_21": 29
 },
 {
  "input_set_index": 2,
  "input_set_size": 547,
  "input_set_id": 61100,
  "operator": "by_distribution",
  "parameter": "",
  "output_set_count": 4,
  "output_set_average_size": 704.25,
  "reward": 0.416158118067613,
  "sets_viewed": 156,
  "sets_reviewed": 3,
  "uniformity": -0.5267267861351238,
  "diversity": 0.9859634407939836,
  "novelty": 0.8154882106352771,
  "utility": 0.416158118067613,
  "utility_weights": [
   0.3472055196531937,
   0.3472055196531937,
   0.3055889606936126
  ],
  "extrinsic_reward": 0,
  "inverted_entropy_score": 6303.110260586031,
  "galaxy_class_score": 16.479927703079163,
  "class_score_found_12": 130,
  "class_score_found_15": 90,
  "class_score_found_18": 57,
  "class_score_found_21": 29
 },
 {
  "input_set_index": 2,
  "input_set_size": 588,
  "input_set_id": 58331,
  "operator": "by_superset",
  "parameter": "",
  "output_set_count": 3,
  "output_set_average_size": 4379.333333333333,
  "reward": 0.2345001881878338,
  "sets_viewed": 159,
  "sets_reviewed": 3,
  "uniformity": -0.8054501878607694,
  "diversity": 0.763100611814912,
  "novelty": 0.8154882106352771,
  "utility": 0.2345001881878338,
  "utility_weights": [
   0.3519226177623247,
   0.3519226177623247,
   0.2961547644753506
  ],
  "extrinsic_reward": 0,
  "inverted_entropy_score": 6303.806485825758,
  "galaxy_class_score": 16.479927703079163,
  "class_score_found_12": 130,
  "class_score_found_15": 90,
  "class_score_found_18": 57,
  "class_score_found_21": 29
 },
 {
  "input_set_index": 0,
  "input_set_size": 8287,
  "input_set_id": 7094,
  "operator": "by_distribution",
  "parameter": "",
  "output_set_count": 7,
  "output_set_average_size": 7388.428571428572,
  "reward": 0.27374665651656616,
  "sets_viewed": 166,
  "sets_reviewed": 3,
  "uniformity": -0.6815081736989661,
  "diversity": 0.773107678636786,
  "novelty": 0.8154882106352771,
  "utility": 0.27374665651656616,
  "utility_weights": [
   0.3626415590986245,
   0.3626415590986245,
   0.274716881802751
  ],
  "extrinsic_reward": 0.05986365722007007,
  "inverted_entropy_score": 6305.599991403386,
  "galaxy_class_score": 16.479927703079163,
  "class_score_found_12": 130,
  "class_score_found_15": 90,
  "class_score_found_18": 57,
  "class_score_found_21": 29
 },
 {
  "input_set_index": 5,
  "input_set_size": 10884,
  "input_set_id": 5315,
  "operator": "by_superset",
  "parameter": "",
  "output_set_count": 3,
  "output_set_average_size": 33142.333333333336,
  "reward": 0.32889209186878354,
  "sets_viewed": 169,
  "sets_reviewed": 3,
  "uniformity": -0.15766310629018523,
  "diversity": 0.44682939422696394,
  "novelty": 0.8154882106352771,
  "utility": 0.32889209186878354,
  "utility_weights": [
   0.36711212499203605,
   0.36711212499203605,
   0.26577575001592785
  ],
  "extrinsic_reward": 5.345810407555391e-05,
  "inverted_entropy_score": 6306.356177732561,
  "galaxy_class_score": 16.479927703079163,
  "class_score_found_12": 130,
  "class_score_found_15": 90,
  "class_score_found_18": 57,
  "class_score_found_21": 29
 }
]