[
 {
  "input_set_index": 6,
  "input_set_size": 10,
  "input_set_id": 340632,
  "operator": "by_superset",
  "parameter": "",
  "output_set_count": 3,
  "output_set_average_size": 135.0,
  "reward": 0.8152578822022434,
  "sets_viewed": 3,
  "sets_reviewed": 0,
  "uniformity": 0.595077585008306,
  "diversity": 0.5752419701946976,
  "novelty": 0.8154882106352771,
  "utility": 0.8152578822022434,
  "utility_weights": [
   0.00856300067435295,
   0.00856300067435295,
   0.9828739986512941
  ],
  "extrinsic_reward": 0.6148302032997871,
  "inverted_entropy_score": 768.7464160974254,
  "galaxy_class_score": 10.185916135342998,
  "galaxy_class_mean_distance": 0.5529416382432227,
  "class_distance_found": 164,
  "class_distance_found_0.1": 0,
  "class_distance_found_0.06": 0,
  "class_distance_found_0.05": 0,
  "class_distance_found_0.04": 0,
  "class_distance_found_0.03": 0,
  "class_distance_found_0.02": 0,
  "class_score_found": 169,
  "class_score_found_3": 169,
  "class_score_found_4": 169,
  "class_score_found_5": 164,
  "class_score_found_8": 133,
  "class_score_found_12": 32,
  "class_score_found_15": 8,
  "class_score_found_18": 4,
  "class_score_found_21": 2
 },
 {
  "input_set_index": 0,
  "input_set_size": 198,
  "input_set_id": 108153,
  "operator": "by_facet",
  "parameter": "galaxies.z",
  "output_set_count": 2,
  "output_set_average_size": 99.0,
  "reward": 0.8126565387355024,
  "sets_viewed": 5,
  "sets_reviewed": 0,
  "uniformity": 0.7514433201908097,
  "diversity": 0.548846230032788,
  "novelty": 0.8154882106352771,
  "utility": 0.8126565387355024,
  "utility_weights": [
   0.014230579087968376,
   0.014230579087968376,
   0.9715388418240632
  ],
  "extrinsic_reward": 0,
  "inverted_entropy_score": 771.7091535926145,
  "galaxy_class_score": 10.185916135342998,
  "galaxy_class_mean_distance": 0.5527129777115596,
  "class_distance_found": 164,
  "class_distance_found_0.1": 0,
  "class_distance_found_0.06": 0,
  "class_distance_found_0.05": 0,
  "class_distance_found_0.04": 0,
  "class_distance_found_0.03": 0,
  "class_distance_found_0.02": 0,
  "class_score_found": 169,
  "class_score_found_3": 169,
  "class_score_found_4": 169,
  "class_score_found_5": 164,
  "class_score_found_8": 133,
  "class_score_found_12": 32,
  "class_score_found_15": 8,
  "class_score_found_18": 4,
  "class_score_found_21": 2
 },
 {
  "input_set_index": 0,
  "input_set_size": 159,
  "input_set_id": 120644,
  "operator": "by_facet",
  "parameter": "galaxies.u",
  "output_set_count": 3,
  "output_set_average_size": 51.333333333333336,
  "reward": 0.8098935327132578,
  "sets_viewed": 8,
  "sets_reviewed": 0,
  "uniformity": 1.432240531461595,
  "diversity": -0.19440889280564658,
  "novelty": 0.8154882106352771,
  "utility": 0.8098935327132578,
  "utility_weights": [
   0.02267031365446165,
   0.02267031365446165,
   0.9546593726910767
  ],
  "extrinsic_reward": 0,
  "inverted_entropy_score": 1147.1375368414517,
  "galaxy_class_score": 10.185916135342998,
  "galaxy_class_mean_distance": 0.5527129777115596,
  "class_distance_found": 164,
  "class_distance_found_0.1": 0,
  "class_distance_found_0.06": 0,
  "class_distance_found_0.05": 0,
  "class_distance_found_0.04": 0,
  "class_distance_found_0.03": 0,
  "class_distance_found_0.02": 0,
  "class_score_found": 169,
  "class_score_found_3": 169,
  "class_score_found_4": 169,
  "class_score_found_5": 164,
  "class_score_found_8": 133,
  "class_score_found_12": 32,
  "class_score_found_15": 8,
  "class_score_found_18": 4,
  "class_score_found_21": 2
 },
 {
  "input_set_index": 2,
  "input_set_size": 11,
  "input_set_id": 333191,
  "operator": "by_superset",
  "parameter": "",
  "output_set_count": 3,
  "output_set_average_size": 136.66666666666666,
  "reward": 0.2079020712257064,
  "sets_viewed": 10,
  "sets_reviewed": 1,
  "uniformity": 0.7514433201908097,
  "diversity": 0.37276825754058557,
  "novelty": 0.19107950685106548,
  "utility": 0.2079020712257064,
  "utility_weights": [
   0.028255714662837217,
   0.028255714662837217,
   0.9434885706743256
  ],
  "extrinsic_reward": 0,
  "inverted_entropy_score": 1148.786833356861,
  "galaxy_class_score": 10.185916135342998,
  "galaxy_class_mean_distance": 0.5527129777115596,
  "class_distance_found": 164,
  "class_distance_found_0.1": 0,
  "class_distance_found_0.06": 0,
  "class_distance_found_0.05": 0,
  "class_distance_found_0.04": 0,
  "class_distance_found_0.03": 0,
  "class_distance_found_0.02": 0,
  "class_score_found": 169,
  "class_score_found_3": 169,
  "class_score_found_4": 169,
  "class_score_found_5": 164,
  "class_score_found_8": 133,
  "class_score_found_12": 32,
  "class_score_found_15": 8,
  "class_score_found_18": 4,
  "class_score_found_21": 2
 },
 {
  "input_set_index": 1,
  "input_set_size": 159,
  "input_set_id": 120644,
  "operator": "by_superset",
  "parameter": "",
  "output_set_count": 3,
  "output_set_average_size": 859.3333333333334,
  "reward": 0.7691501065411134,
  "sets_viewed": 13,
  "sets_reviewed": 1,
  "uniformity": 0.10115388717608421,
  "diversity": -0.11013259169497035,
  "novelty": 0.8154882106352771,
  "utility": 0.7691501065411134,
  "utility_weights": [
   0.03657218312147076,
   0.03657218312147076,
   0.9268556337570585
  ],
  "extrinsic_reward": 0.00021893690328255314,
  "inverted_entropy_score": 1150.033696253496,
  "galaxy_class_score": 10.185916135342998,
  "galaxy_class_mean_distance": 0.5527129777115596,
  "class_distance_found": 164,
  "class_distance_found_0.1": 0,
  "class_distance_found_0.06": 0,
  "class_distance_found_0.05": 0,
  "class_distance_found_0.04": 0,
  "class_distance_found_0.03": 0,
  "class_distance_found_0.02": 0,
  "class_score_found": 169,
  "class_score_found_3": 169,
  "class_score_found_4": 169,
  "class_score_found_5": 164,
  "class_score_found_8": 133,
  "class_score_found_12": 32,
  "class_score_found_15": 8,
  "class_score_found_18": 4,
  "class_score_found_21": 2
 },
 {
  "input_set_index": 2,
  "input_set_size": 237,
  "input_set_id": 98643,
  "operator": "by_superset",
  "parameter": "",
  "output_set_count": 3,
  "output_set_average_size": 1267.6666666666667,
  "reward": 0.7729122231069407,
  "sets_viewed": 16,
  "sets_reviewed": 1,
  "uniformity": -0.13689007366878558,
  "diversity": 0.6037033552403898,
  "novelty": 0.8154882106352771,
  "utility": 0.7729122231069407,
  "utility_weights": [
   0.04481469191538867,
   0.04481469191538867,
   0.9103706161692227
  ],
  "extrinsic_reward": 0.005603960169320034,
  "inverted_entropy_score": 1150.9350663442344,
  "galaxy_class_score": 10.185916135342998,
  "galaxy_class_mean_distance": 0.5524245608113546,
  "class_distance_found": 164,
  "class_distance_found_0.1": 0,
  "class_distance_found_0.06": 0,
  "class_distance_found_0.05": 0,
  "class_distance_found_0.04": 0,
  "class_distance_found_0.03": 0,
  "class_distance_found_0.02": 0,
  "class_score_found": 169,
  "class_score_found_3": 169,
  "class_score_found_4": 169,
  "class_score_found_5": 164,
  "class_score_found_8": 133,
  "class_score_found_12": 32,
  "class_score_found_15": 8,
  "class_score_found_18": 4,
  "class_score_found_21": 2
 },
 {
  "input_set_index": 2,
  "input_set_size": 610,
  "input_set_id": 57103,
  "operator": "by_facet",
  "parameter": "galaxies.g",
  "output_set_count": 2,
  "output_set_average_size": 302.0,
  "reward": 0.8163138973461818,
  "sets_viewed": 18,
  "sets_reviewed": 1,
  "uniformity": 0.6988259446844328,
  "diversity": 0.9505749413233453,
  "novelty": 0.8154882106352771,
  "utility": 0.8163138973461818,
  "utility_weights": [
   0.050268609075380555,
   0.050268609075380555,
   0.8994627818492389
  ],
  "extrinsic_reward": 0.00901068520842084,
  "inverted_entropy_score": 1152.33056536404,
  "galaxy_class_score": 10.455015199826693,
  "galaxy_class_mean_distance": 0.551355879092771,
  "class_distance_found": 164,
  "class_distance_found_0.1": 1,
  "class_distance_found_0.06": 1,
  "class_distance_found_0.05": 1,
  "class_distance_found_0.04": 0,
  "class_distance_found_0.03": 0,
  "class_distance_found_0.02": 0,
  "class_score_found": 169,
  "class_score_found_3": 169,
  "class_score_found_4": 169,
  "class_score_found_5": 164,
  "class_score_found_8": 133,
  "class_score_found_12": 32,
  "class_score_found_15": 8,
  "class_score_found_18": 4,
  "class_score_found_21": 3
 },
 {
  "input_set_index": 0,
  "input_set_size": 385,
  "input_set_id": 75484,
  "operator": "by_facet",
  "parameter": "galaxies.i",
  "output_set_count": 2,
  "output_set_average_size": 192.5,
  "reward": 0.793817362732394,
  "sets_viewed": 20,
  "sets_reviewed": 1,
  "uniformity": 0.9208974511177401,
  "diversity": 0.27897796494325156,
  "novelty": 0.8154882106352771,
  "utility": 0.793817362732394,
  "utility_weights": [
   0.05568965527327663,
   0.05568965527327663,
   0.8886206894534467
  ],
  "extrinsic_reward": 0.014171066165351137,
  "inverted_entropy_score": 1154.977721790505,
  "galaxy_class_score": 10.687649059122098,
  "galaxy_class_mean_distance": 0.5510860920441648,
  "class_distance_found": 164,
  "class_distance_found_0.1": 1,
  "class_distance_found_0.06": 1,
  "class_distance_found_0.05": 1,
  "class_distance_found_0.04": 1,
  "class_distance_found_0.03": 0,
  "class_distance_found_0.02": 0,
  "class_score_found": 169,
  "class_score_found_3": 169,
  "class_score_found_4": 169,
  "class_score_found_5": 164,
  "class_score_found_8": 133,
  "class_score_found_12": 32,
  "class_score_found_15": 8,
  "class_score_found_18": 4,
  "class_score_found_21": 3
 },
 {
  "input_set_index": 0,
  "input_set_size": 307,
  "input_set_id": 85639,
  "operator": "by_facet",
  "parameter": "galaxies.u",
  "output_set_count": 3,
  "output_set_average_size": 102.0,
  "reward": 0.7934976623269878,
  "sets_viewed": 23,
  "sets_reviewed": 1,
  "uniformity": 1.2757171831075078,
  "diversity": -0.039617479970306645,
  "novelty": 0.8154882106352771,
  "utility": 0.7934976623269878,
  "utility_weights": [
   0.06375959151619087,
   0.06375959151619087,
   0.8724808169676183
  ],
  "extrinsic_reward": 1.5881198751702488,
  "inverted_entropy_score": 1530.406105039342,
  "galaxy_class_score": 10.946599890998822,
  "galaxy_class_mean_distance": 0.5504062122979334,
  "class_distance_found": 164,
  "class_distance_found_0.1": 2,
  "class_distance_found_0.06": 1,
  "class_distance_found_0.05": 1,
  "class_distance_found_0.04": 1,
  "class_distance_found_0.03": 1,
  "class_distance_found_0.02": 0,
  "class_score_found": 169,
  "class_score_found_3": 169,
  "class_score_found_4": 169,
  "class_score_found_5": 164,
  "class_score_found_8": 133,
  "class_score_found_12": 32,
  "class_score_found_15": 8,
  "class_score_found_18": 4,
  "class_score_found_21": 3
 },
 {
  "input_set_index": 0,
  "input_set_size": 227,
  "input_set_id": 100700,
  "operator": "by_superset",
  "parameter": "",
  "output_set_count": 3,
  "output_set_average_size": 668.6666666666666,
  "reward": 0.7352834433997201,
  "sets_viewed": 26,
  "sets_reviewed": 1,
  "uniformity": 0.6960071857226056,
  "diversity": -0.3229554990418292,
  "novelty": 0.8154882106352771,
  "utility": 0.7352834433997201,
  "utility_weights": [
   0.07175556809438932,
   0.07175556809438932,
   0.8564888638112214
  ],
  "extrinsic_reward": 0.07289836216218805,
  "inverted_entropy_score": 1532.963719748941,
  "galaxy_class_score": 10.946599890998822,
  "galaxy_class_mean_distance": 0.5503596345908762,
  "class_distance_found": 164,
  "class_distance_found_0.1": 2,
  "class_distance_found_0.06": 1,
  "class_distance_found_0.05": 1,
  "class_distance_found_0.04": 1,
  "class_distance_found_0.03": 1,
  "class_distance_found_0.02": 0,
  "class_score_found": 169,
  "class_score_found_3": 169,
  "class_score_found_4": 169,
  "class_score_found_5": 164,
  "class_score_found_8": 133,
  "class_score_found_12": 32,
  "class_score_found_15": 8,
  "class_score_found_18": 4,
  "class_score_found_21": 3
 },
 {
  "input_set_index": 2,
  "input_set_size": 413,
  "input_set_id": 72446,
  "operator": "by_superset",
  "parameter": "",
  "output_set_count": 3,
  "output_set_average_size": 1610.0,
  "reward": 0.7272443911900214,
  "sets_viewed": 29,
  "sets_reviewed": 1,
  "uniformity": 0.20469621967168877,
  "diversity": 0.19649662119187403,
  "novelty": 0.8154882106352771,
  "utility": 0.7272443911900214,
  "utility_weights": [
   0.07967758500787192,
   0.07967758500787192,
   0.8406448299842562
  ],
  "extrinsic_reward": 0.012308881660024659,
  "inverted_entropy_score": 1534.3037754205518,
  "galaxy_class_score": 10.95289086823003,
  "galaxy_class_mean_distance": 0.5502736809072314,
  "class_distance_found": 164,
  "class_distance_found_0.1": 2,
  "class_distance_found_0.06": 1,
  "class_distance_found_0.05": 1,
  "class_distance_found_0.04": 1,
  "class_distance_found_0.03": 1,
  "class_distance_found_0.02": 0,
  "class_score_found": 169,
  "class_score_found_3": 169,
  "class_score_found_4": 169,
  "class_score_found_5": 164,
  "class_score_found_8": 133,
  "class_score_found_12": 32,
  "class_score_found_15": 8,
  "class_score_found_18": 4,
  "class_score_found_21": 3
 },
 {
  "input_set_index": 2,
  "input_set_size": 813,
  "input_set_id": 47512,
  "operator": "by_superset",
  "parameter": "",
  "output_set_count": 3,
  "output_set_average_size": 3164.0,
  "reward": 0.6798099214578941,
  "sets_viewed": 32,
  "sets_reviewed": 1,
  "uniformity": -0.09936528774147926,
  "diversity": 0.027500324399555385,
  "novelty": 0.8154882106352771,
  "utility": 0.6798099214578941,
  "utility_weights": [
   0.08752564225663872,
   0.08752564225663872,
   0.8249487154867226
  ],
  "extrinsic_reward": 0.012858258335672779,
  "inverted_entropy_score": 1535.2230887914834,
  "galaxy_class_score": 10.95289086823003,
  "galaxy_class_mean_distance": 0.5502736809072314,
  "class_distance_found": 164,
  "class_distance_found_0.1": 2,
  "class_distance_found_0.06": 1,
  "class_distance_found_0.05": 1,
  "class_distance_found_0.04": 1,
  "class_distance_found_0.03": 1,
  "class_distance_found_0.02": 0,
  "class_score_found": 169,
  "class_score_found_3": 169,
  "class_score_found_4": 169,
  "class_score_found_5": 164,
  "class_score_found_8": 133,
  "class_score_found_12": 32,
  "class_score_found_15": 8,
  "class_score_found_18": 4,
  "class_score_found_21": 3
 },
 {
  "input_set_index": 2,
  "input_set_size": 1215,
  "input_set_id": 36108,
  "operator": "by_facet",
  "parameter": "galaxies.z",
  "output_set_count": 3,
  "output_set_average_size": 401.3333333333333,
  "reward": 0.743989426671776,
  "sets_viewed": 35,
  "sets_reviewed": 1,
  "uniformity": -0.04588318344464938,
  "diversity": 0.8599700381827395,
  "novelty": 0.8154882106352771,
  "utility": 0.743989426671776,
  "utility_weights": [
   0.09529973984068973,
   0.09529973984068973,
   0.8094005203186205
  ],
  "extrinsic_reward": 0.0022452033218874766,
  "inverted_entropy_score": 1537.0484114673486,
  "galaxy_class_score": 10.95289086823003,
  "galaxy_class_mean_distance": 0.5502736809072314,
  "class_distance_found": 164,
  "class_distance_found_0.1": 2,
  "class_distance_found_0.06": 1,
  "class_distance_found_0.05": 1,
  "class_distance_found_0.04": 1,
  "class_distance_found_0.03": 1,
  "class_distance_found_0.02": 0,
  "class_score_found": 169,
  "class_score_found_3": 169,
  "class_score_found_4": 169,
  "class_score_found_5": 164,
  "class_score_found_8": 133,
  "class_score_found_12": 32,
  "class_score_found_15": 8,
  "class_score_found_18": 4,
  "class_score_found_21": 3
 },
 {
  "input_set_index": 1,
  "input_set_size": 372,
  "input_set_id": 76852,
  "operator": "by_facet",
  "parameter": "galaxies.u",
  "output_set_count": 4,
  "output_set_average_size": 92.0,
  "reward": 0.8027396365653348,
  "sets_viewed": 39,
  "sets_reviewed": 1,
  "uniformity": 1.2019588149643075,
  "diversity": 0.29524416588286506,
  "novelty": 0.8154882106352771,
  "utility": 0.8027396365653348,
  "utility_weights": [
   0.10555015491875547,
   0.10555015491875547,
   0.7888996901624891
  ],
  "extrinsic_reward": 0,
  "inverted_entropy_score": 1686.3713262707718,
  "galaxy_class_score": 10.95289086823003,
  "galaxy_class_mean_distance": 0.5502545808453227,
  "class_distance_found": 164,
  "class_distance_found_0.1": 2,
  "class_distance_found_0.06": 1,
  "class_distance_found_0.05": 1,
  "class_distance_found_0.04": 1,
  "class_distance_found_0.03": 1,
  "class_distance_found_0.02": 0,
  "class_score_found": 169,
  "class_score_found_3": 169,
  "class_score_found_4": 169,
  "class_score_found_5": 164,
  "class_score_found_8": 133,
  "class_score_found_12": 32,
  "class_score_found_15": 8,
  "class_score_found_18": 4,
  "class_score_found_21": 3
 },
 {
  "input_set_index": 0,
  "input_set_size": 229,
  "input_set_id": 100342,
  "operator": "by_superset",
  "parameter": "",
  "output_set_count": 3,
  "output_set_average_size": 679.0,
  "reward": 0.6886901130953901,
  "sets_viewed": 42,
  "sets_reviewed": 1,
  "uniformity": 0.6906753189709045,
  "diversity": -0.2610054958525428,
  "novelty": 0.8154882106352771,
  "utility": 0.6886901130953901,
  "utility_weights": [
   0.11315167995180281,
   0.11315167995180281,
   0.7736966400963944
  ],
  "extrinsic_reward": 0,
  "inverted_entropy_score": 1688.783098419585,
  "galaxy_class_score": 10.95289086823003,
  "galaxy_class_mean_distance": 0.5502545808453227,
  "class_distance_found": 164,
  "class_distance_found_0.1": 2,
  "class_distance_found_0.06": 1,
  "class_distance_found_0.05": 1,
  "class_distance_found_0.04": 1,
  "class_distance_found_0.03": 1,
  "class_distance_found_0.02": 0,
  "class_score_found": 169,
  "class_score_found_3": 169,
  "class_score_found_4": 169,
  "class_score_found_5": 164,
  "class_score_found_8": 133,
  "class_score_found_12": 32,
  "class_score_found_15": 8,
  "class_score_found_18": 4,
  "class_score_found_21": 3
 },
 {
  "input_set_index": 1,
  "input_set_size": 772,
  "input_set_id": 49177,
  "operator": "by_superset",
  "parameter": "",
  "output_set_count": 3,
  "output_set_average_size": 2002.6666666666667,
  "reward": 0.5874982747256972,
  "sets_viewed": 45,
  "sets_reviewed": 1,
  "uniformity": -0.556052346866308,
  "diversity": 0.1721233243405991,
  "novelty": 0.8154882106352771,
  "utility": 0.5874982747256972,
  "utility_weights": [
   0.12067924532013458,
   0.12067924532013458,
   0.7586415093597308
  ],
  "extrinsic_reward": 0.024135197427512318,
  "inverted_entropy_score": 1689.7419612163326,
  "galaxy_class_score": 10.95289086823003,
  "galaxy_class_mean_distance": 0.5502545808453227,
  "class_distance_found": 164,
  "class_distance_found_0.1": 2,
  "class_distance_found_0.06": 1,
  "class_distance_found_0.05": 1,
  "class_distance_found_0.04": 1,
  "class_distance_found_0.03": 1,
  "class_distance_found_0.02": 0,
  "class_score_found": 169,
  "class_score_found_3": 169,
  "class_score_found_4": 169,
  "class_score_found_5": 164,
  "class_score_found_8": 133,
  "class_score_found_12": 32,
  "class_score_found_15": 8,
  "class_score_found_18": 4,
  "class_score_found_21": 3
 },
 {
  "input_set_index": 1,
  "input_set_size": 1595,
  "input_set_id": 29684,
  "operator": "by_facet",
  "parameter": "galaxies.g",
  "output_set_count": 4,
  "output_set_average_size": 398.25,
  "reward": 0.7367923081950769,
  "sets_viewed": 49,
  "sets_reviewed": 1,
  "uniformity": -0.028512688484656393,
  "diversity": 1.00738110036687,
  "novelty": 0.8154882106352771,
  "utility": 0.7367923081950769,
  "utility_weights": [
   0.13060095077724104,
   0.13060095077724104,
   0.7387980984455179
  ],
  "extrinsic_reward": 2.3340919302232113,
  "inverted_entropy_score": 1692.3513698496304,
  "galaxy_class_score": 10.960123200693669,
  "galaxy_class_mean_distance": 0.5499142757958771,
  "class_distance_found": 164,
  "class_distance_found_0.1": 2,
  "class_distance_found_0.06": 1,
  "class_distance_found_0.05": 1,
  "class_distance_found_0.04": 1,
  "class_distance_found_0.03": 1,
  "class_distance_found_0.02": 0,
  "class_score_found": 169,
  "class_score_found_3": 169,
  "class_score_found_4": 169,
  "class_score_found_5": 164,
  "class_score_found_8": 133,
  "class_score_found_12": 33,
  "class_score_found_15": 8,
  "class_score_found_18": 4,
  "class_score_found_21": 3
 },
 {
  "input_set_index": 2,
  "input_set_size": 93,
  "input_set_id": 153684,
  "operator": "by_facet",
  "parameter": "galaxies.u",
  "output_set_count": 5,
  "output_set_average_size": 17.2,
  "reward": 0.7141292502493681,
  "sets_viewed": 54,
  "sets_reviewed": 1,
  "uniformity": 1.558521542403546,
  "diversity": -0.7036417711397092,
  "novelty": 0.8154882106352771,
  "utility": 0.7141292502493681,
  "utility_weights": [
   0.14281818343683467,
   0.14281818343683467,
   0.7143636331263307
  ],
  "extrinsic_reward": 0,
  "inverted_entropy_score": 1699.4988154839873,
  "galaxy_class_score": 10.960123200693669,
  "galaxy_class_mean_distance": 0.5499142757958771,
  "class_distance_found": 164,
  "class_distance_found_0.1": 2,
  "class_distance_found_0.06": 1,
  "class_distance_found_0.05": 1,
  "class_distance_found_0.04": 1,
  "class_distance_found_0.03": 1,
  "class_distance_found_0.02": 0,
  "class_score_found": 169,
  "class_score_found_3": 169,
  "class_score_found_4": 169,
  "class_score_found_5": 164,
  "class_score_found_8": 133,
  "class_score_found_12": 33,
  "class_score_found_15": 8,
  "class_score_found_18": 4,
  "class_score_found_21": 3
 },
 {
  "input_set_index": 0,
  "input_set_size": 31,
  "input_set_id": 236890,
  "operator": "by_facet",
  "parameter": "galaxies.redshift",
  "output_set_count": 2,
  "output_set_average_size": 15.0,
  "reward": 0.7540103478024546,
  "sets_viewed": 56,
  "sets_reviewed": 1,
  "uniformity": 2.203403987805613,
  "diversity": -1.0028900003330128,
  "novelty": 0.8154882106352771,
  "utility": 0.7540103478024546,
  "utility_weights": [
   0.14764755231700422,
   0.14764755231700422,
   0.7047048953659916
  ],
  "extrinsic_reward": 0,
  "inverted_entropy_score": 1949.7844043165453,
  "galaxy_class_score": 10.960123200693669,
  "galaxy_class_mean_distance": 0.5499142757958771,
  "class_distance_found": 164,
  "class_distance_found_0.1": 2,
  "class_distance_found_0.06": 1,
  "class_distance_found_0.05": 1,
  "class_distance_found_0.04": 1,
  "class_distance_found_0.03": 1,
  "class_distance_found_0.02": 0,
  "class_score_found": 169,
  "class_score_found_3": 169,
  "class_score_found_4": 169,
  "class_score_found_5": 164,
  "class_score_found_8": 133,
  "class_score_found_12": 33,
  "class_score_found_15": 8,
  "class_score_found_18": 4,
  "class_score_found_21": 3
 },
 {
  "input_set_index": 1,
  "input_set_size": 11,
  "input_set_id": 334133,
  "operator": "by_superset",
  "parameter": "",
  "output_set_count": 3,
  "output_set_average_size": 73.33333333333333,
  "reward": 0.6020842938692719,
  "sets_viewed": 59,
  "sets_reviewed": 1,
  "uniformity": 0.6949941990754286,
  "diversity": -0.5093781201681529,
  "novelty": 0.8154882106352771,
  "utility": 0.6020842938692719,
  "utility_weights": [
   0.15482997258332876,
   0.15482997258332876,
   0.6903400548333425
  ],
  "extrinsic_reward": 0,
  "inverted_entropy_score": 1952.4268733477886,
  "galaxy_class_score": 10.960123200693669,
  "galaxy_class_mean_distance": 0.5499142757958771,
  "class_distance_found": 164,
  "class_distance_found_0.1": 2,
  "class_distance_found_0.06": 1,
  "class_distance_found_0.05": 1,
  "class_distance_found_0.04": 1,
  "class_distance_found_0.03": 1,
  "class_distance_found_0.02": 0,
  "class_score_found": 169,
  "class_score_found_3": 169,
  "class_score_found_4": 169,
  "class_score_found_5": 164,
  "class_score_found_8": 133,
  "class_score_found_12": 33,
  "class_score_found_15": 8,
  "class_score_found_18": 4,
  "class_score_found_21": 3
 },
 {
  "input_set_index": 2,
  "input_set_size": 35,
  "input_set_id": 227399,
  "operator": "by_superset",
  "parameter": "",
  "output_set_count": 3,
  "output_set_average_size": 333.3333333333333,
  "reward": 0.6532817492202045,
  "sets_viewed": 62,
  "sets_reviewed": 1,
  "uniformity": 0.4644767356034442,
  "diversity": 0.11885717363492708,
  "novelty": 0.8154882106352771,
  "utility": 0.6532817492202045,
  "utility_weights": [
   0.1619384331849376,
   0.1619384331849376,
   0.6761231336301248
  ],
  "extrinsic_reward": 0,
  "inverted_entropy_score": 1954.6276678303852,
  "galaxy_class_score": 10.960123200693669,
  "galaxy_class_mean_distance": 0.5499142757958771,
  "class_distance_found": 164,
  "class_distance_found_0.1": 2,
  "class_distance_found_0.06": 1,
  "class_distance_found_0.05": 1,
  "class_distance_found_0.04": 1,
  "class_distance_found_0.03": 1,
  "class_distance_found_0.02": 0,
  "class_score_found": 169,
  "class_score_found_3": 169,
  "class_score_found_4": 169,
  "class_score_found_5": 164,
  "class_score_found_8": 133,
  "class_score_found_12": 33,
  "class_score_found_15": 8,
  "class_score_found_18": 4,
  "class_score_found_21": 3
 },
 {
  "input_set_index": 1,
  "input_set_size": 278,
  "input_set_id": 90462,
  "operator": "by_facet",
  "parameter": "galaxies.z",
  "output_set_count": 2,
  "output_set_average_size": 139.0,
  "reward": 0.7060503489241464,
  "sets_viewed": 64,
  "sets_reviewed": 1,
  "uniformity": 0.7891633366195075,
  "diversity": 0.16601389628820767,
  "novelty": 0.8154882106352771,
  "utility": 0.7060503489241464,
  "utility_weights": [
   0.16663631821672348,
   0.16663631821672348,
   0.666727363566553
  ],
  "extrinsic_reward": 0,
  "inverted_entropy_score": 1959.2826993699816,
  "galaxy_class_score": 10.960123200693669,
  "galaxy_class_mean_distance": 0.5499142757958771,
  "class_distance_found": 164,
  "class_distance_found_0.1": 2,
  "class_distance_found_0.06": 1,
  "class_distance_found_0.05": 1,
  "class_distance_found_0.04": 1,
  "class_distance_found_0.03": 1,
  "class_distance_found_0.02": 0,
  "class_score_found": 169,
  "class_score_found_3": 169,
  "class_score_found_4": 169,
  "class_score_found_5": 164,
  "class_score_found_8": 133,
  "class_score_found_12": 33,
  "class_score_found_15": 8,
  "class_score_found_18": 4,
  "class_score_found_21": 3
 },
 {
  "input_set_index": 0,
  "input_set_size": 250,
  "input_set_id": 95914,
  "operator": "by_facet",
  "parameter": "galaxies.g",
  "output_set_count": 2,
  "output_set_average_size": 125.0,
  "reward": 0.7409852257986957,
  "sets_viewed": 66,
  "sets_reviewed": 1,
  "uniformity": 0.817165893891859,
  "diversity": 0.3667112057309116,
  "novelty": 0.8154882106352771,
  "utility": 0.7409852257986957,
  "utility_weights": [
   0.17130133228641353,
   0.17130133228641353,
   0.6573973354271729
  ],
  "extrinsic_reward": 0,
  "inverted_entropy_score": 2209.56828820254,
  "galaxy_class_score": 10.960123200693669,
  "galaxy_class_mean_distance": 0.5499142757958771,
  "class_distance_found": 164,
  "class_distance_found_0.1": 2,
  "class_distance_found_0.06": 1,
  "class_distance_found_0.05": 1,
  "class_distance_found_0.04": 1,
  "class_distance_found_0.03": 1,
  "class_distance_found_0.02": 0,
  "class_score_found": 169,
  "class_score_found_3": 169,
  "class_score_found_4": 169,
  "class_score_found_5": 164,
  "class_score_found_8": 133,
  "class_score_found_12": 33,
  "class_score_found_15": 8,
  "class_score_found_18": 4,
  "class_score_found_21": 3
 },
 {
  "input_set_index": 0,
  "input_set_size": 226,
  "input_set_id": 100937,
  "operator": "by_superset",
  "parameter": "",
  "output_set_count": 3,
  "output_set_average_size": 4618.333333333333,
  "reward": 0.5036997032017272,
  "sets_viewed": 69,
  "sets_reviewed": 1,
  "uniformity": 0.07622027726369213,
  "diversity": -0.2653610919305893,
  "novelty": 0.8154882106352771,
  "utility": 0.5036997032017272,
  "utility_weights": [
   0.17823722033701872,
   0.17823722033701872,
   0.6435255593259626
  ],
  "extrinsic_reward": 0,
  "inverted_entropy_score": 2211.70065575838,
  "galaxy_class_score": 10.960123200693669,
  "galaxy_class_mean_distance": 0.5499142757958771,
  "class_distance_found": 164,
  "class_distance_found_0.1": 2,
  "class_distance_found_0.06": 1,
  "class_distance_found_0.05": 1,
  "class_distance_found_0.04": 1,
  "class_distance_found_0.03": 1,
  "class_distance_found_0.02": 0,
  "class_score_found": 169,
  "class_score_found_3": 169,
  "class_score_found_4": 169,
  "class_score_found_5": 164,
  "class_score_found_8": 133,
  "class_score_found_12": 33,
  "class_score_found_15": 8,
  "class_score_found_18": 4,
  "class_score_found_21": 3
 },
 {
  "input_set_index": 2,
  "input_set_size": 338,
  "input_set_id": 81241,
  "operator": "by_superset",
  "parameter": "",
  "output_set_count": 3,
  "output_set_average_size": 8758.666666666666,
  "reward": 0.5922206204774023,
  "sets_viewed": 72,
  "sets_reviewed": 1,
  "uniformity": -0.18312803355268006,
  "diversity": 0.561461545919523,
  "novelty": 0.8154882106352771,
  "utility": 0.5922206204774023,
  "utility_weights": [
   0.1850991487229081,
   0.1850991487229081,
   0.6298017025541838
  ],
  "extrinsic_reward": 1.4492283149068785e-05,
  "inverted_entropy_score": 2213.1015694035978,
  "galaxy_class_score": 10.960123200693669,
  "galaxy_class_mean_distance": 0.5499142757958771,
  "class_distance_found": 164,
  "class_distance_found_0.1": 2,
  "class_distance_found_0.06": 1,
  "class_distance_found_0.05": 1,
  "class_distance_found_0.04": 1,
  "class_distance_found_0.03": 1,
  "class_distance_found_0.02": 0,
  "class_score_found": 169,
  "class_score_found_3": 169,
  "class_score_found_4": 169,
  "class_score_found_5": 164,
  "class_score_found_8": 133,
  "class_score_found_12": 33,
  "class_score_found_15": 8,
  "class_score_found_18": 4,
  "class_score_found_21": 3
 },
 {
  "input_set_index": 2,
  "input_set_size": 400,
  "input_set_id": 73744,
  "operator": "by_superset",
  "parameter": "",
  "output_set_count": 3,
  "output_set_average_size": 10598.0,
  "reward": 0.5420247783045502,
  "sets_viewed": 75,
  "sets_reviewed": 1,
  "uniformity": -0.39650850610616,
  "diversity": 0.5500960024816602,
  "novelty": 0.8154882106352771,
  "utility": 0.5420247783045502,
  "utility_weights": [
   0.1918871174440817,
   0.1918871174440817,
   0.6162257651118366
  ],
  "extrinsic_reward": 0.00021126667938628843,
  "inverted_entropy_score": 2214.156412997104,
  "galaxy_class_score": 10.960123200693669,
  "galaxy_class_mean_distance": 0.5499142757958771,
  "class_distance_found": 164,
  "class_distance_found_0.1": 2,
  "class_distance_found_0.06": 1,
  "class_distance_found_0.05": 1,
  "class_distance_found_0.04": 1,
  "class_distance_found_0.03": 1,
  "class_distance_found_0.02": 0,
  "class_score_found": 169,
  "class_score_found_3": 169,
  "class_score_found_4": 169,
  "class_score_found_5": 164,
  "class_score_found_8": 133,
  "class_score_found_12": 33,
  "class_score_found_15": 8,
  "class_score_found_18": 4,
  "class_score_found_21": 3
 },
 {
  "input_set_index": 2,
  "input_set_size": 457,
  "input_set_id": 68230,
  "operator": "by_facet",
  "parameter": "galaxies.g",
  "output_set_count": 2,
  "output_set_average_size": 226.5,
  "reward": 0.6916100535019866,
  "sets_viewed": 77,
  "sets_reviewed": 1,
  "uniformity": 0.51368721386315,
  "diversity": 0.47171091750792665,
  "novelty": 0.8154882106352771,
  "utility": 0.6916100535019866,
  "utility_weights": [
   0.19637134122224414,
   0.19637134122224414,
   0.6072573175555117
  ],
  "extrinsic_reward": 0,
  "inverted_entropy_score": 2215.7155976049035,
  "galaxy_class_score": 10.960123200693669,
  "galaxy_class_mean_distance": 0.5499142757958771,
  "class_distance_found": 164,
  "class_distance_found_0.1": 2,
  "class_distance_found_0.06": 1,
  "class_distance_found_0.05": 1,
  "class_distance_found_0.04": 1,
  "class_distance_found_0.03": 1,
  "class_distance_found_0.02": 0,
  "class_score_found": 169,
  "class_score_found_3": 169,
  "class_score_found_4": 169,
  "class_score_found_5": 164,
  "class_score_found_8": 133,
  "class_score_found_12": 33,
  "class_score_found_15": 8,
  "class_score_found_18": 4,
  "class_score_found_21": 3
 },
 {
  "input_set_index": 0,
  "input_set_size": 363,
  "input_set_id": 78087,
  "operator": "by_facet",
  "parameter": "galaxies.redshift",
  "output_set_count": 3,
  "output_set_average_size": 118.33333333333333,
  "reward": 0.6042041758463463,
  "sets_viewed": 80,
  "sets_reviewed": 1,
  "uniformity": 0.5566556141238346,
  "diversity": -0.0016204858844721217,
  "novelty": 0.8154882106352771,
  "utility": 0.6042041758463463,
  "utility_weights": [
   0.20303604383555812,
   0.20303604383555812,
   0.5939279123288838
  ],
  "extrinsic_reward": 0,
  "inverted_entropy_score": 2226.66753177696,
  "galaxy_class_score": 10.960123200693669,
  "galaxy_class_mean_distance": 0.5499142757958771,
  "class_distance_found": 164,
  "class_distance_found_0.1": 2,
  "class_distance_found_0.06": 1,
  "class_distance_found_0.05": 1,
  "class_distance_found_0.04": 1,
  "class_distance_found_0.03": 1,
  "class_distance_found_0.02": 0,
  "class_score_found": 169,
  "class_score_found_3": 169,
  "class_score_found_4": 169,
  "class_score_found_5": 164,
  "class_score_found_8": 133,
  "class_score_found_12": 33,
  "class_score_found_15": 8,
  "class_score_found_18": 4,
  "class_score_found_21": 3
 },
 {
  "input_set_index": 2,
  "input_set_size": 34,
  "input_set_id": 231058,
  "operator": "by_superset",
  "parameter": "",
  "output_set_count": 3,
  "output_set_average_size": 648.3333333333334,
  "reward": 0.2126534563039788,
  "sets_viewed": 82,
  "sets_reviewed": 2,
  "uniformity": -0.5013676454995932,
  "diversity": 0.9897834057643512,
  "novelty": 0.19107950685106548,
  "utility": 0.2126534563039788,
  "utility_weights": [
   0.2074380902084808,
   0.2074380902084808,
   0.5851238195830384
  ],
  "extrinsic_reward": 0,
  "inverted_entropy_score": 2227.6674219139854,
  "galaxy_class_score": 10.960123200693669,
  "galaxy_class_mean_distance": 0.5499142757958771,
  "class_distance_found": 164,
  "class_distance_found_0.1": 2,
  "class_distance_found_0.06": 1,
  "class_distance_found_0.05": 1,
  "class_distance_found_0.04": 1,
  "class_distance_found_0.03": 1,
  "class_distance_found_0.02": 0,
  "class_score_found": 169,
  "class_score_found_3": 169,
  "class_score_found_4": 169,
  "class_score_found_5": 164,
  "class_score_found_8": 133,
  "class_score_found_12": 33,
  "class_score_found_15": 8,
  "class_score_found_18": 4,
  "class_score_found_21": 3
 },
 {
  "input_set_index": 0,
  "input_set_size": 1322,
  "input_set_id": 34051,
  "operator": "by_facet",
  "parameter": "galaxies.z",
  "output_set_count": 3,
  "output_set_average_size": 439.6666666666667,
  "reward": 0.6749390769448035,
  "sets_viewed": 85,
  "sets_reviewed": 2,
  "uniformity": 0.4639894603041516,
  "diversity": 0.48943958502778906,
  "novelty": 0.8154882106352771,
  "utility": 0.6749390769448035,
  "utility_weights": [
   0.21397952671393505,
   0.21397952671393505,
   0.5720409465721299
  ],
  "extrinsic_reward": 0.00012088077800315423,
  "inverted_entropy_score": 2230.570379141398,
  "galaxy_class_score": 10.960123200693669,
  "galaxy_class_mean_distance": 0.5499142757958771,
  "class_distance_found": 164,
  "class_distance_found_0.1": 2,
  "class_distance_found_0.06": 1,
  "class_distance_found_0.05": 1,
  "class_distance_found_0.04": 1,
  "class_distance_found_0.03": 1,
  "class_distance_found_0.02": 0,
  "class_score_found": 169,
  "class_score_found_3": 169,
  "class_score_found_4": 169,
  "class_score_found_5": 164,
  "class_score_found_8": 133,
  "class_score_found_12": 33,
  "class_score_found_15": 8,
  "class_score_found_18": 4,
  "class_score_found_21": 3
 },
 {
  "input_set_index": 1,
  "input_set_size": 194,
  "input_set_id": 109312,
  "operator": "by_facet",
  "parameter": "galaxies.u",
  "output_set_count": 3,
  "output_set_average_size": 61.333333333333336,
  "reward": 0.658401036807867,
  "sets_viewed": 88,
  "sets_reviewed": 2,
  "uniformity": 1.2694809740499913,
  "diversity": -0.372627000098506,
  "novelty": 0.8154882106352771,
  "utility": 0.658401036807867,
  "utility_weights": [
   0.22044700355467345,
   0.22044700355467345,
   0.5591059928906531
  ],
  "extrinsic_reward": 0,
  "inverted_entropy_score": 2605.9987623902357,
  "galaxy_class_score": 10.960123200693669,
  "galaxy_class_mean_distance": 0.5499142757958771,
  "class_distance_found": 164,
  "class_distance_found_0.1": 2,
  "class_distance_found_0.06": 1,
  "class_distance_found_0.05": 1,
  "class_distance_found_0.04": 1,
  "class_distance_found_0.03": 1,
  "class_distance_found_0.02": 0,
  "class_score_found": 169,
  "class_score_found_3": 169,
  "class_score_found_4": 169,
  "class_score_found_5": 164,
  "class_score_found_8": 133,
  "class_score_found_12": 33,
  "class_score_found_15": 8,
  "class_score_found_18": 4,
  "class_score_found_21": 3
 },
 {
  "input_set_index": 0,
  "input_set_size": 82,
  "input_set_id": 162678,
  "operator": "by_superset",
  "parameter": "",
  "output_set_count": 3,
  "output_set_average_size": 516.6666666666666,
  "reward": 0.5645664946664068,
  "sets_viewed": 91,
  "sets_reviewed": 2,
  "uniformity": 0.6701457221227473,
  "diversity": -0.1774098390441248,
  "novelty": 0.8154882106352771,
  "utility": 0.5645664946664068,
  "utility_weights": [
   0.22684052073069616,
   0.22684052073069616,
   0.5463189585386077
  ],
  "extrinsic_reward": 0.0001780308282175373,
  "inverted_entropy_score": 2610.9360276156503,
  "galaxy_class_score": 10.960123200693669,
  "galaxy_class_mean_distance": 0.5499142757958771,
  "class_distance_found": 164,
  "class_distance_found_0.1": 2,
  "class_distance_found_0.06": 1,
  "class_distance_found_0.05": 1,
  "class_distance_found_0.04": 1,
  "class_distance_found_0.03": 1,
  "class_distance_found_0.02": 0,
  "class_score_found": 169,
  "class_score_found_3": 169,
  "class_score_found_4": 169,
  "class_score_found_5": 164,
  "class_score_found_8": 133,
  "class_score_found_12": 33,
  "class_score_found_15": 8,
  "class_score_found_18": 4,
  "class_score_found_21": 3
 },
 {
  "input_set_index": 1,
  "input_set_size": 337,
  "input_set_id": 81306,
  "operator": "by_superset",
  "parameter": "",
  "output_set_count": 3,
  "output_set_average_size": 2438.3333333333335,
  "reward": 0.5237479144936983,
  "sets_viewed": 94,
  "sets_reviewed": 2,
  "uniformity": 0.07546076745148489,
  "diversity": 0.26941255723902174,
  "novelty": 0.8154882106352771,
  "utility": 0.5237479144936983,
  "utility_weights": [
   0.2331600782420029,
   0.2331600782420029,
   0.5336798435159942
  ],
  "extrinsic_reward": 1.1740219721545372e-05,
  "inverted_entropy_score": 2612.008458629633,
  "galaxy_class_score": 10.960123200693669,
  "galaxy_class_mean_distance": 0.5499142757958771,
  "class_distance_found": 164,
  "class_distance_found_0.1": 2,
  "class_distance_found_0.06": 1,
  "class_distance_found_0.05": 1,
  "class_distance_found_0.04": 1,
  "class_distance_found_0.03": 1,
  "class_distance_found_0.02": 0,
  "class_score_found": 169,
  "class_score_found_3": 169,
  "class_score_found_4": 169,
  "class_score_found_5": 164,
  "class_score_found_8": 133,
  "class_score_found_12": 33,
  "class_score_found_15": 8,
  "class_score_found_18": 4,
  "class_score_found_21": 3
 },
 {
  "input_set_index": 1,
  "input_set_size": 1189,
  "input_set_id": 36625,
  "operator": "by_superset",
  "parameter": "",
  "output_set_count": 3,
  "output_set_average_size": 4325.0,
  "reward": 0.4220516747191257,
  "sets_viewed": 97,
  "sets_reviewed": 2,
  "uniformity": -0.2360900196436005,
  "diversity": 0.1796569200278501,
  "novelty": 0.8154882106352771,
  "utility": 0.4220516747191257,
  "utility_weights": [
   0.23940567608859398,
   0.23940567608859398,
   0.521188647822812
  ],
  "extrinsic_reward": 2.135575626601158e-05,
  "inverted_entropy_score": 2612.776305855587,
  "galaxy_class_score": 10.960123200693669,
  "galaxy_class_mean_distance": 0.5499142757958771,
  "class_distance_found": 164,
  "class_distance_found_0.1": 2,
  "class_distance_found_0.06": 1,
  "class_distance_found_0.05": 1,
  "class_distance_found_0.04": 1,
  "class_distance_found_0.03": 1,
  "class_distance_found_0.02": 0,
  "class_score_found": 169,
  "class_score_found_3": 169,
  "class_score_found_4": 169,
  "class_score_found_5": 164,
  "class_score_found_8": 133,
  "class_score_found_12": 33,
  "class_score_found_15": 8,
  "class_score_found_18": 4,
  "class_score_found_21": 3
 },
 {
  "input_set_index": 0,
  "input_set_size": 6351,
  "input_set_id": 9225,
  "operator": "by_facet",
  "parameter": "galaxies.z",
  "output_set_count": 4,
  "output_set_average_size": 1587.0,
  "reward": 0.40713131848728024,
  "sets_viewed": 100,
  "sets_reviewed": 3,
  "uniformity": 0.051105917084772245,
  "diversity": 0.8630346704206826,
  "novelty": 0.361252828284015,
  "utility": 0.40713131848728024,
  "utility_weights": [
   0.24557731427046908,
   0.24557731427046908,
   0.5088453714590618
  ],
  "extrinsic_reward": 1.6501758159152555e-05,
  "inverted_entropy_score": 2614.0234214816305,
  "galaxy_class_score": 10.960123200693669,
  "galaxy_class_mean_distance": 0.5499142757958771,
  "class_distance_found": 164,
  "class_distance_found_0.1": 2,
  "class_distance_found_0.06": 1,
  "class_distance_found_0.05": 1,
  "class_distance_found_0.04": 1,
  "class_distance_found_0.03": 1,
  "class_distance_found_0.02": 0,
  "class_score_found": 169,
  "class_score_found_3": 169,
  "class_score_found_4": 169,
  "class_score_found_5": 164,
  "class_score_found_8": 133,
  "class_score_found_12": 33,
  "class_score_found_15": 8,
  "class_score_found_18": 4,
  "class_score_found_21": 3
 },
 {
  "input_set_index": 0,
  "input_set_size": 4241,
  "input_set_id": 13299,
  "operator": "by_facet",
  "parameter": "galaxies.i",
  "output_set_count": 2,
  "output_set_average_size": 2117.5,
  "reward": 0.6840536675442714,
  "sets_viewed": 102,
  "sets_reviewed": 3,
  "uniformity": 0.2145002147711381,
  "diversity": 0.8812698358236261,
  "novelty": 0.8154882106352771,
  "utility": 0.6840536675442714,
  "utility_weights": [
   0.24965065102243267,
   0.24965065102243267,
   0.5006986979551347
  ],
  "extrinsic_reward": 1.6785518564357232e-05,
  "inverted_entropy_score": 2614.9586077982335,
  "galaxy_class_score": 10.960123200693669,
  "galaxy_class_mean_distance": 0.5499142757958771,
  "class_distance_found": 164,
  "class_distance_found_0.1": 2,
  "class_distance_found_0.06": 1,
  "class_distance_found_0.05": 1,
  "class_distance_found_0.04": 1,
  "class_distance_found_0.03": 1,
  "class_distance_found_0.02": 0,
  "class_score_found": 169,
  "class_score_found_3": 169,
  "class_score_found_4": 169,
  "class_score_found_5": 164,
  "class_score_found_8": 133,
  "class_score_found_12": 33,
  "class_score_found_15": 8,
  "class_score_found_18": 4,
  "class_score_found_21": 3
 },
 {
  "input_set_index": 1,
  "input_set_size": 30,
  "input_set_id": 242010,
  "operator": "by_superset",
  "parameter": "",
  "output_set_count": 3,
  "output_set_average_size": 1742.6666666666667,
  "reward": 0.2449730347090069,
  "sets_viewed": 104,
  "sets_reviewed": 4,
  "uniformity": 0.028038899537890915,
  "diversity": 0.5699958895216164,
  "novelty": 0.19107950685106548,
  "utility": 0.2449730347090069,
  "utility_weights": [
   0.2536911168123004,
   0.2536911168123004,
   0.4926177663753993
  ],
  "extrinsic_reward": 0,
  "inverted_entropy_score": 2615.6928072028154,
  "galaxy_class_score": 10.960123200693669,
  "galaxy_class_mean_distance": 0.5499142757958771,
  "class_distance_found": 164,
  "class_distance_found_0.1": 2,
  "class_distance_found_0.06": 1,
  "class_distance_found_0.05": 1,
  "class_distance_found_0.04": 1,
  "class_distance_found_0.03": 1,
  "class_distance_found_0.02": 0,
  "class_score_found": 169,
  "class_score_found_3": 169,
  "class_score_found_4": 169,
  "class_score_found_5": 164,
  "class_score_found_8": 133,
  "class_score_found_12": 33,
  "class_score_found_15": 8,
  "class_score_found_18": 4,
  "class_score_found_21": 3
 },
 {
  "input_set_index": 2,
  "input_set_size": 95,
  "input_set_id": 152850,
  "operator": "by_superset",
  "parameter": "",
  "output_set_count": 3,
  "output_set_average_size": 19755.0,
  "reward": 0.33571733066576853,
  "sets_viewed": 107,
  "sets_reviewed": 4,
  "uniformity": -1.3036596907791786,
  "diversity": 1.043474584606583,
  "novelty": 0.8154882106352771,
  "utility": 0.33571733066576853,
  "utility_weights": [
   0.259690182443172,
   0.259690182443172,
   0.48061963511365596
  ],
  "extrinsic_reward": 0,
  "inverted_entropy_score": 2616.470189832337,
  "galaxy_class_score": 10.960123200693669,
  "galaxy_class_mean_distance": 0.5499142757958771,
  "class_distance_found": 164,
  "class_distance_found_0.1": 2,
  "class_distance_found_0.06": 1,
  "class_distance_found_0.05": 1,
  "class_distance_found_0.04": 1,
  "class_distance_found_0.03": 1,
  "class_distance_found_0.02": 0,
  "class_score_found": 169,
  "class_score_found_3": 169,
  "class_score_found_4": 169,
  "class_score_found_5": 164,
  "class_score_found_8": 133,
  "class_score_found_12": 33,
  "class_score_found_15": 8,
  "class_score_found_18": 4,
  "class_score_found_21": 3
 },
 {
  "input_set_index": 1,
  "input_set_size": 2045,
  "input_set_id": 24606,
  "operator": "by_superset",
  "parameter": "",
  "output_set_count": 3,
  "output_set_average_size": 30384.333333333332,
  "reward": 0.39548420378277294,
  "sets_viewed": 110,
  "sets_reviewed": 4,
  "uniformity": -0.7717800696092767,
  "diversity": 0.7854292476968369,
  "novelty": 0.8154882106352771,
  "utility": 0.39548420378277294,
  "utility_weights": [
   0.26561528840932785,
   0.26561528840932785,
   0.4687694231813443
  ],
  "extrinsic_reward": 0.00031759202399247305,
  "inverted_entropy_score": 2617.0814244297535,
  "galaxy_class_score": 10.960123200693669,
  "galaxy_class_mean_distance": 0.5497966332853892,
  "class_distance_found": 164,
  "class_distance_found_0.1": 2,
  "class_distance_found_0.06": 1,
  "class_distance_found_0.05": 1,
  "class_distance_found_0.04": 1,
  "class_distance_found_0.03": 1,
  "class_distance_found_0.02": 0,
  "class_score_found": 169,
  "class_score_found_3": 169,
  "class_score_found_4": 169,
  "class_score_found_5": 164,
  "class_score_found_8": 133,
  "class_score_found_12": 33,
  "class_score_found_15": 8,
  "class_score_found_18": 4,
  "class_score_found_21": 3
 },
 {
  "input_set_index": 2,
  "input_set_size": 7907,
  "input_set_id": 7446,
  "operator": "by_superset",
  "parameter": "",
  "output_set_count": 3,
  "output_set_average_size": 51901.333333333336,
  "reward": 0.4662020889486528,
  "sets_viewed": 113,
  "sets_reviewed": 4,
  "uniformity": -0.9831140163393248,
  "diversity": 1.2990828423077776,
  "novelty": 0.8154882106352771,
  "utility": 0.4662020889486528,
  "utility_weights": [
   0.2714664347107679,
   0.2714664347107679,
   0.4570671305784642
  ],
  "extrinsic_reward": 0.00019620904520817968,
  "inverted_entropy_score": 2617.533197746364,
  "galaxy_class_score": 10.960123200693669,
  "galaxy_class_mean_distance": 0.5497966332853892,
  "class_distance_found": 164,
  "class_distance_found_0.1": 2,
  "class_distance_found_0.06": 1,
  "class_distance_found_0.05": 1,
  "class_distance_found_0.04": 1,
  "class_distance_found_0.03": 1,
  "class_distance_found_0.02": 0,
  "class_score_found": 169,
  "class_score_found_3": 169,
  "class_score_found_4": 169,
  "class_score_found_5": 164,
  "class_score_found_8": 133,
  "class_score_found_12": 33,
  "class_score_found_15": 8,
  "class_score_found_18": 4,
  "class_score_found_21": 3
 },
 {
  "input_set_index": 2,
  "input_set_size": 23086,
  "input_set_id": 2245,
  "operator": "by_superset",
  "parameter": "",
  "output_set_count": 2,
  "output_set_average_size": 261638.5,
  "reward": 0.5712312213301294,
  "sets_viewed": 115,
  "sets_reviewed": 4,
  "uniformity": -1.015486672626446,
  "diversity": 1.746694437173786,
  "novelty": 0.8154882106352771,
  "utility": 0.5712312213301294,
  "utility_weights": [
   0.275326110209108,
   0.275326110209108,
   0.4493477795817839
  ],
  "extrinsic_reward": 4.0482677881955575e-05,
  "inverted_entropy_score": 2617.7806777815194,
  "galaxy_class_score": 10.960123200693669,
  "galaxy_class_mean_distance": 0.5497966332853892,
  "class_distance_found": 164,
  "class_distance_found_0.1": 2,
  "class_distance_found_0.06": 1,
  "class_distance_found_0.05": 1,
  "class_distance_found_0.04": 1,
  "class_distance_found_0.03": 1,
  "class_distance_found_0.02": 0,
  "class_score_found": 169,
  "class_score_found_3": 169,
  "class_score_found_4": 169,
  "class_score_found_5": 164,
  "class_score_found_8": 133,
  "class_score_found_12": 33,
  "class_score_found_15": 8,
  "class_score_found_18": 4,
  "class_score_found_21": 3
 },
 {
  "input_set_index": 0,
  "input_set_size": 261640,
  "input_set_id": 7,
  "operator": "by_facet",
  "parameter": "galaxies.redshift",
  "output_set_count": 10,
  "output_set_average_size": 26164.0,
  "reward": 0.0637758024976206,
  "sets_viewed": 125,
  "sets_reviewed": 4,
  "uniformity": -1.959149419126447,
  "diversity": 0.8598638700857336,
  "novelty": 0.8154882106352771,
  "utility": 0.0637758024976206,
  "utility_weights": [
   0.29413142326937,
   0.29413142326937,
   0.41173715346126005
  ],
  "extrinsic_reward": 0.006580123381166864,
  "inverted_entropy_score": 2619.163567985442,
  "galaxy_class_score": 10.960123200693669,
  "galaxy_class_mean_distance": 0.5486629959200743,
  "class_distance_found": 164,
  "class_distance_found_0.1": 2,
  "class_distance_found_0.06": 1,
  "class_distance_found_0.05": 1,
  "class_distance_found_0.04": 1,
  "class_distance_found_0.03": 1,
  "class_distance_found_0.02": 0,
  "class_score_found": 169,
  "class_score_found_3": 169,
  "class_score_found_4": 169,
  "class_score_found_5": 164,
  "class_score_found_8": 133,
  "class_score_found_12": 33,
  "class_score_found_15": 8,
  "class_score_found_18": 4,
  "class_score_found_21": 3
 },
 {
  "input_set_index": 9,
  "input_set_size": 980,
  "input_set_id": 41852,
  "operator": "by_superset",
  "parameter": "",
  "output_set_count": 2,
  "output_set_average_size": 261639.0,
  "reward": 0.3876789380196869,
  "sets_viewed": 126,
  "sets_reviewed": 5,
  "uniformity": -1.1518520581103016,
  "diversity": 2.735400399056198,
  "novelty": -0.1896656365890159,
  "utility": 0.3876789380196869,
  "utility_weights": [
   0.29596675700251435,
   0.29596675700251435,
   0.4080664859949713
  ],
  "extrinsic_reward": 0,
  "inverted_entropy_score": 2619.2878315119583,
  "galaxy_class_score": 10.960123200693669,
  "galaxy_class_mean_distance": 0.5486629959200743,
  "class_distance_found": 164,
  "class_distance_found_0.1": 2,
  "class_distance_found_0.06": 1,
  "class_distance_found_0.05": 1,
  "class_distance_found_0.04": 1,
  "class_distance_found_0.03": 1,
  "class_distance_found_0.02": 0,
  "class_score_found": 169,
  "class_score_found_3": 169,
  "class_score_found_4": 169,
  "class_score_found_5": 164,
  "class_score_found_8": 133,
  "class_score_found_12": 33,
  "class_score_found_15": 8,
  "class_score_found_18": 4,
  "class_score_found_21": 3
 },
 {
  "input_set_index": 1,
  "input_set_size": 261638,
  "input_set_id": 24,
  "operator": "by_facet",
  "parameter": "galaxies.r",
  "output_set_count": 10,
  "output_set_average_size": 26163.8,
  "reward": -0.14993475295850955,
  "sets_viewed": 136,
  "sets_reviewed": 5,
  "uniformity": -2.4701014932345786,
  "diversity": 0.8391475093090349,
  "novelty": 0.8154882106352771,
  "utility": -0.14993475295850955,
  "utility_weights": [
   0.31386811860513864,
   0.31386811860513864,
   0.3722637627897228
  ],
  "extrinsic_reward": 0,
  "inverted_entropy_score": 2620.6071528656366,
  "galaxy_class_score": 10.960123200693669,
  "galaxy_class_mean_distance": 0.5486629959200743,
  "class_distance_found": 164,
  "class_distance_found_0.1": 2,
  "class_distance_found_0.06": 1,
  "class_distance_found_0.05": 1,
  "class_distance_found_0.04": 1,
  "class_distance_found_0.03": 1,
  "class_distance_found_0.02": 0,
  "class_score_found": 169,
  "class_score_found_3": 169,
  "class_score_found_4": 169,
  "class_score_found_5": 164,
  "class_score_found_8": 133,
  "class_score_found_12": 33,
  "class_score_found_15": 8,
  "class_score_found_18": 4,
  "class_score_found_21": 3
 },
 {
  "input_set_index": 9,
  "input_set_size": 37,
  "input_set_id": 224000,
  "operator": "by_facet",
  "parameter": "galaxies.z",
  "output_set_count": 2,
  "output_set_average_size": 14.0,
  "reward": 0.6161652195685325,
  "sets_viewed": 138,
  "sets_reviewed": 5,
  "uniformity": -2.5453691814809467,
  "diversity": 3.5412922817816743,
  "novelty": 0.8154882106352771,
  "utility": 0.6161652195685325,
  "utility_weights": [
   0.31734977803937575,
   0.31734977803937575,
   0.3653004439212485
  ],
  "extrinsic_reward": 0,
  "inverted_entropy_score": 2621.2255188780746,
  "galaxy_class_score": 10.960123200693669,
  "galaxy_class_mean_distance": 0.5255809615716586,
  "class_distance_found": 169,
  "class_distance_found_0.1": 2,
  "class_distance_found_0.06": 1,
  "class_distance_found_0.05": 1,
  "class_distance_found_0.04": 1,
  "class_distance_found_0.03": 1,
  "class_distance_found_0.02": 0,
  "class_score_found": 169,
  "class_score_found_3": 169,
  "class_score_found_4": 169,
  "class_score_found_5": 164,
  "class_score_found_8": 133,
  "class_score_found_12": 33,
  "class_score_found_15": 8,
  "class_score_found_18": 4,
  "class_score_found_21": 3
 },
 {
  "input_set_index": 1,
  "input_set_size": 11,
  "input_set_id": 338089,
  "operator": "by_superset",
  "parameter": "",
  "output_set_count": 3,
  "output_set_average_size": 53291.333333333336,
  "reward": 0.19460406867484434,
  "sets_viewed": 140,
  "sets_reviewed": 6,
  "uniformity": -2.4701014932345786,
  "diversity": 2.8633667438641592,
  "novelty": 0.19107950685106548,
  "utility": 0.19460406867484434,
  "utility_weights": [
   0.32079856651151695,
   0.32079856651151695,
   0.35840286697696616
  ],
  "extrinsic_reward": 0.22822142167853035,
  "inverted_entropy_score": 2621.5615899750364,
  "galaxy_class_score": 10.960123200693669,
  "galaxy_class_mean_distance": 0.5255809615716586,
  "class_distance_found": 169,
  "class_distance_found_0.1": 2,
  "class_distance_found_0.06": 1,
  "class_distance_found_0.05": 1,
  "class_distance_found_0.04": 1,
  "class_distance_found_0.03": 1,
  "class_distance_found_0.02": 0,
  "class_score_found": 169,
  "class_score_found_3": 169,
  "class_score_found_4": 169,
  "class_score_found_5": 164,
  "class_score_found_8": 133,
  "class_score_found_12": 33,
  "class_score_found_15": 8,
  "class_score_found_18": 4,
  "class_score_found_21": 3
 },
 {
  "input_set_index": 1,
  "input_set_size": 204,
  "input_set_id": 106507,
  "operator": "by_superset",
  "parameter": "",
  "output_set_count": 2,
  "output_set_average_size": 261634.0,
  "reward": 0.9267190745937665,
  "sets_viewed": 142,
  "sets_reviewed": 6,
  "uniformity": -1.1913016522768298,
  "diversity": 3.169009248714578,
  "novelty": 0.8154882106352771,
  "utility": 0.9267190745937665,
  "utility_weights": [
   0.3242144840215622,
   0.3242144840215622,
   0.35157103195687556
  ],
  "extrinsic_reward": 0.26863071425578383,
  "inverted_entropy_score": 2621.9313558069875,
  "galaxy_class_score": 16.101433850922053,
  "galaxy_class_mean_distance": 0.16719597395681512,
  "class_distance_found": 169,
  "class_distance_found_0.1": 51,
  "class_distance_found_0.06": 17,
  "class_distance_found_0.05": 10,
  "class_distance_found_0.04": 9,
  "class_distance_found_0.03": 5,
  "class_distance_found_0.02": 1,
  "class_score_found": 169,
  "class_score_found_3": 169,
  "class_score_found_4": 169,
  "class_score_found_5": 164,
  "class_score_found_8": 144,
  "class_score_found_12": 102,
  "class_score_found_15": 57,
  "class_score_found_18": 34,
  "class_score_found_21": 25
 },
 {
  "input_set_index": 0,
  "input_set_size": 261638,
  "input_set_id": 26,
  "operator": "by_facet",
  "parameter": "galaxies.i",
  "output_set_count": 7,
  "output_set_average_size": 37374.57142857143,
  "reward": -0.006658278479392266,
  "sets_viewed": 149,
  "sets_reviewed": 6,
  "uniformity": -2.280538394331038,
  "diversity": 1.3757043270732894,
  "novelty": 0.8154882106352771,
  "utility": -0.006658278479392266,
  "utility_weights": [
   0.3359113364802155,
   0.3359113364802155,
   0.32817732703956903
  ],
  "extrinsic_reward": 1.9623837533290662,
  "inverted_entropy_score": 2623.3225011895647,
  "galaxy_class_score": 16.89133733301153,
  "galaxy_class_mean_distance": 0.1607103136385067,
  "class_distance_found": 169,
  "class_distance_found_0.1": 54,
  "class_distance_found_0.06": 17,
  "class_distance_found_0.05": 12,
  "class_distance_found_0.04": 9,
  "class_distance_found_0.03": 7,
  "class_distance_found_0.02": 1,
  "class_score_found": 169,
  "class_score_found_3": 169,
  "class_score_found_4": 169,
  "class_score_found_5": 164,
  "class_score_found_8": 145,
  "class_score_found_12": 106,
  "class_score_found_15": 63,
  "class_score_found_18": 38,
  "class_score_found_21": 27
 },
 {
  "input_set_index": 6,
  "input_set_size": 15,
  "input_set_id": 302228,
  "operator": "by_superset",
  "parameter": "",
  "output_set_count": 2,
  "output_set_average_size": 261636.0,
  "reward": 0.6354829826830742,
  "sets_viewed": 150,
  "sets_reviewed": 7,
  "uniformity": -1.0360596165034675,
  "diversity": 3.113176011684166,
  "novelty": -0.1896656365890159,
  "utility": 0.6354829826830742,
  "utility_weights": [
   0.3375494444407843,
   0.3375494444407843,
   0.32490111111843145
  ],
  "extrinsic_reward": 2.774970527871915e-07,
  "inverted_entropy_score": 2623.4364599360492,
  "galaxy_class_score": 16.89133733301153,
  "galaxy_class_mean_distance": 0.1607103136385067,
  "class_distance_found": 169,
  "class_distance_found_0.1": 54,
  "class_distance_found_0.06": 17,
  "class_distance_found_0.05": 12,
  "class_distance_found_0.04": 9,
  "class_distance_found_0.03": 7,
  "class_distance_found_0.02": 1,
  "class_score_found": 169,
  "class_score_found_3": 169,
  "class_score_found_4": 169,
  "class_score_found_5": 164,
  "class_score_found_8": 145,
  "class_score_found_12": 106,
  "class_score_found_15": 63,
  "class_score_found_18": 38,
  "class_score_found_21": 27
 },
 {
  "input_set_index": 0,
  "input_set_size": 261638,
  "input_set_id": 26,
  "operator": "by_facet",
  "parameter": "galaxies.z",
  "output_set_count": 8,
  "output_set_average_size": 32703.375,
  "reward": -0.12359043339569667,
  "sets_viewed": 157,
  "sets_reviewed": 8,
  "uniformity": -2.268331531759001,
  "diversity": 1.3270154269627852,
  "novelty": 0.5975673464245506,
  "utility": -0.12359043339569667,
  "utility_weights": [
   0.34878610343009464,
   0.34878610343009464,
   0.30242779313981066
  ],
  "extrinsic_reward": 3.1593300236275303,
  "inverted_entropy_score": 2625.012527067263,
  "galaxy_class_score": 17.643860072366998,
  "galaxy_class_mean_distance": 0.15610149379242788,
  "class_distance_found": 169,
  "class_distance_found_0.1": 56,
  "class_distance_found_0.06": 18,
  "class_distance_found_0.05": 13,
  "class_distance_found_0.04": 10,
  "class_distance_found_0.03": 8,
  "class_distance_found_0.02": 1,
  "class_score_found": 169,
  "class_score_found_3": 169,
  "class_score_found_4": 169,
  "class_score_found_5": 164,
  "class_score_found_8": 145,
  "class_score_found_12": 111,
  "class_score_found_15": 68,
  "class_score_found_18": 41,
  "class_score_found_21": 29
 }
]